{"metadata": {"dataVersion": "2", "matchId": "KR_8148515863", "participants": ["wdeVEW_I7UKRqxE27JyO_OGK23ET43qKqyMPd_2Cnm8-qaAPQD3gfPATlu-ysoo4DPLcmA1VejMIuA", "MstO4vI4ZxH5lFz0BAzR4DioM00Evm0yfhTewKJh-_VXxMLAa67pFg9aynNHd5mUPC0T8bRU9scJcw", "I4SKg4yOf9T5TvsvDoql-pBh7mk2yph6ne2fT1nFWL9Bvvfy9sjcKuSai-fuxHH-xz0gEXhUyT0INw", "eNFqceGnXYoJgGaQcS7871WgiazFI_aGhMfPJ8dz_xVScadobkwnfFl72xR0zZpPTFJK8uYGGLALrQ", "6jgyjL46WpaYXSxcgNp9_hZ5VqIcwYtKLCkwnY2TfrgTZOFLwhLZhy6yXPqG6BtTr89uRXIXpDd4FA", "EN-Qok0VumcDOiATZgaoWOwUVvT5raWfNLUJW0IxOJF2JqnsFQu6GHQ3nBPA-d5tjV-lNq7EiyQodw", "k62NydW4IOimX3WWnxx6mVaoW_P0twrcs8G4XEYzF15-qFuKiMrlNgwL6WzHDtagsDaGZKO1i43vMQ", "1bVScljhCg5Rku3G5jTwBjzTLQZRGsLc-l5OOUoYZNxNaCybvTPdrJgCmWLRfaZyAAzWuq20r0rB9w", "DgqLeWUzndH39nqp7y-ziA39kQHcrcxYPXqGyjG9TeNI3XHeaqt75EOoEDOFFuVZ5gW7dV5ra4_GAw", "VQYKg7nVyGyAECILMq0k4VzClnDlA04xcUOhcz_lr4dsUVMQO29EJo_HQwDm1c7FvHt7ciSRiyOG7A"]}, "info": {"endOfGameResult": "GameComplete", "gameCreation": 1774448251106, "gameDuration": 1342, "gameEndTimestamp": 1774449606199, "gameId": 8148515863, "gameMode": "CLASSIC", "gameName": "teambuilder-match-8148515863", "gameStartTimestamp": 1774448263526, "gameType": "MATCHED_GAME", "gameVersion": "16.6.756.931", "mapId": 11, "participants": [{"PlayerBehavior": {"PlayerBehavior_IsHeroInCombat": 0}, "PlayerScore0": 0, "PlayerScore1": 0, "PlayerScore10": 0, "PlayerScore11": 0, "PlayerScore2": 0, "PlayerScore3": 0, "PlayerScore4": 0, "PlayerScore5": 0, "PlayerScore6": 0, "PlayerScore7": 0, "PlayerScore8": 0, "PlayerScore9": 0, "allInPings": 0, "assistMePings": 5, "assists": 3, "baronKills": 0, "basicPings": 0, "challenges": {"12AssistStreakCount": 0, "HealFromMapSources": 0, "InfernalScalePickup": 0, "SWARM_DefeatAatrox": 0, "SWARM_DefeatBriar": 0, "SWARM_DefeatMiniBosses": 0, "SWARM_EvolveWeapon": 0, "SWARM_Have3Passives": 0, "SWARM_KillEnemy": 0, "SWARM_PickupGold": 0, "SWARM_ReachLevel50": 0, "SWARM_Survive15Min": 0, "SWARM_WinWith5EvolvedWeapons": 0, "abilityUses": 207, "acesBefore15Minutes": 0, "alliedJungleMonsterKills": 2, "baronBuffGoldAdvantageOverThreshold": 1, "baronTakedowns": 1, "blastConeOppositeOpponentCount": 0, "bountyGold": 0, "buffsStolen": 0, "completeSupportQuestInTime": 0, "controlWardsPlaced": 0, "damagePerMinute": 726.5749476577591, "damageTakenOnTeamPercentage": 0.2808184278668437, "dancedWithRiftHerald": 0, "deathsByEnemyChamps": 5, "dodgeSkillShotsSmallWindow": 0, "doubleAces": 0, "dragonTakedowns": 0, "earliestBaron": 1228.0247327480001, "earlyLaningPhaseGoldExpAdvantage": 0, "effectiveHealAndShielding": 0, "elderDragonKillsWithOpposingSoul": 0, "elderDragonMultikills": 0, "enemyChampionImmobilizations": 1, "enemyJungleMonsterKills": 0, "epicMonsterKillsNearEnemyJungler": 0, "epicMonsterKillsWithin30SecondsOfSpawn": 0, "epicMonsterSteals": 0, "epicMonsterStolenWithoutSmite": 0, "firstTurretKilled": 1, "firstTurretKilledTime": 708.630564453, "fistBumpParticipation": 0, "flawlessAces": 1, "fullTeamTakedown": 1, "gameLength": 1342.98021752, "getTakedownsInAllLanesEarlyJungleAsLaner": 0, "goldPerMinute": 552.6235534358849, "hadOpenNexus": 0, "immobilizeAndKillWithAlly": 0, "initialBuffCount": 0, "initialCrabCount": 0, "jungleCsBefore10Minutes": 4, "junglerTakedownsNearDamagedEpicMonster": 0, "kTurretsDestroyedBeforePlatesFall": 0, "kda": 2.8, "killAfterHiddenWithAlly": 0, "killParticipation": 0.5384615384615384, "killedChampTookFullTeamDamageSurvived": 0, "killingSprees": 1, "killsNearEnemyTurret": 6, "killsOnOtherLanesEarlyJungleAsLaner": 1, "killsOnRecentlyHealedByAramPack": 0, "killsUnderOwnTurret": 0, "killsWithHelpFromEpicMonster": 0, "knockEnemyIntoTeamAndKill": 0, "landSkillShotsEarlyGame": 5, "laneMinionsFirst10Minutes": 70, "laningPhaseGoldExpAdvantage": 0, "legendaryCount": 0, "legendaryItemUsed": [3153, 3124], "lostAnInhibitor": 0, "maxCsAdvantageOnLaneOpponent": 37, "maxKillDeficit": 1, "maxLevelLeadLaneOpponent": 1, "mejaisFullStackInTime": 0, "moreEnemyJungleThanOpponent": 0, "multiKillOneSpell": 0, "multiTurretRiftHeraldCount": 0, "multikills": 2, "multikillsAfterAggressiveFlash": 0, "outerTurretExecutesBefore10Minutes": 0, "outnumberedKills": 1, "outnumberedNexusKill": 0, "perfectDragonSoulsTaken": 0, "perfectGame": 0, "pickKillWithAlly": 9, "playedChampSelectPosition": 1, "poroExplosions": 0, "quickCleanse": 0, "quickFirstTurret": 0, "quickSoloKills": 0, "riftHeraldTakedowns": 0, "saveAllyFromDeath": 0, "scuttleCrabKills": 1, "shortestTimeToAceFromFirstTakedown": 27.730997661000174, "skillshotsDodged": 7, "skillshotsHit": 16, "snowballsHit": 0, "soloBaronKills": 0, "soloKills": 1, "soloTurretsLategame": 1, "stealthWardsPlaced": 6, "survivedSingleDigitHpCount": 0, "survivedThreeImmobilizesInFight": 2, "takedownOnFirstTurret": 0, "takedowns": 14, "takedownsAfterGainingLevelAdvantage": 0, "takedownsBeforeJungleMinionSpawn": 0, "takedownsFirstXMinutes": 4, "takedownsInAlcove": 0, "takedownsInEnemyFountain": 0, "teamBaronKills": 1, "teamDamagePercentage": 0.2104899297699531, "teamElderDragonKills": 0, "teamRiftHeraldKills": 1, "tookLargeDamageSurvived": 0, "turretPlatesTaken": 15, "turretTakedowns": 4, "turretsTakenWithRiftHerald": 0, "twentyMinionsIn3SecondsCount": 0, "twoWardsOneSweeperCount": 0, "unseenRecalls": 0, "visionScoreAdvantageLaneOpponent": -0.2012012004852295, "visionScorePerMinute": 1.071457756844187, "voidMonsterKill": 2, "wardTakedowns": 2, "wardTakedownsBefore20M": 2, "wardsGuarded": 0}, "champExperience": 14359, "champLevel": 15, "championId": 429, "championName": "Kalista", "championTransform": 0, "commandPings": 13, "consumablesPurchased": 1, "damageDealtToBuildings": 10122, "damageDealtToEpicMonsters": 5370, "damageDealtToObjectives": 15492, "damageDealtToTurrets": 10122, "damageSelfMitigated": 9888, "dangerPings": 0, "deaths": 5, "detectorWardsPlaced": 0, "doubleKills": 1, "dragonKills": 0, "eligibleForProgression": true, "enemyMissingPings": 6, "enemyVisionPings": 0, "firstBloodAssist": false, "firstBloodKill": false, "firstTowerAssist": false, "firstTowerKill": false, "gameEndedInEarlySurrender": false, "gameEndedInSurrender": true, "getBackPings": 4, "goldEarned": 12369, "goldSpent": 9850, "holdPings": 0, "individualPosition": "TOP", "inhibitorKills": 0, "inhibitorTakedowns": 0, "inhibitorsLost": 0, "item0": 3153, "item1": 3124, "item2": 1043, "item3": 1055, "item4": 3006, "item5": 3051, "item6": 3363, "itemsPurchased": 17, "killingSprees": 2, "kills": 11, "lane": "TOP", "largestCriticalStrike": 0, "largestKillingSpree": 7, "largestMultiKill": 3, "longestTimeSpentLiving": 298, "magicDamageDealt": 3947, "magicDamageDealtToChampions": 635, "magicDamageTaken": 8645, "missions": {"playerScore0": 0, "playerScore1": 0, "playerScore2": 0, "playerScore3": 0, "playerScore4": 0, "playerScore5": 0, "playerScore6": 0, "playerScore7": 0, "playerScore8": 0, "playerScore9": 0, "playerScore10": 0, "playerScore11": 0}, "needVisionPings": 1, "neutralMinionsKilled": 8, "nexusKills": 0, "nexusLost": 0, "nexusTakedowns": 0, "objectivesStolen": 0, "objectivesStolenAssists": 0, "onMyWayPings": 30, "participantId": 1, "pentaKills": 0, "perks": {"statPerks": {"defense": 5011, "flex": 5008, "offense": 5005}, "styles": [{"description": "primaryStyle", "selections": [{"perk": 8008, "var1": 540, "var2": 540, "var3": 0}, {"perk": 8009, "var1": 1195, "var2": 0, "var3": 0}, {"perk": 9104, "var1": 16, "var2": 30, "var3": 0}, {"perk": 8017, "var1": 495, "var2": 0, "var3": 0}], "style": 8000}, {"description": "subStyle", "selections": [{"perk": 8143, "var1": 820, "var2": 0, "var3": 0}, {"perk": 8135, "var1": 450, "var2": 5, "var3": 0}], "style": 8100}]}, "physicalDamageDealt": 125285, "physicalDamageDealtToChampions": 14806, "physicalDamageTaken": 9893, "placement": 0, "playerAugment1": 0, "playerAugment2": 0, "playerAugment3": 0, "playerAugment4": 0, "playerAugment5": 0, "playerAugment6": 0, "playerSubteamId": 0, "profileIcon": 4025, "pushPings": 0, "puuid": "wdeVEW_I7UKRqxE27JyO_OGK23ET43qKqyMPd_2Cnm8-qaAPQD3gfPATlu-ysoo4DPLcmA1VejMIuA", "quadraKills": 0, "retreatPings": 0, "riotIdGameName": "iwwinn", "riotIdTagline": "jin", "role": "SOLO", "roleBoundItem": 1220, "sightWardsBoughtInGame": 0, "spell1Casts": 78, "spell2Casts": 5, "spell3Casts": 121, "spell4Casts": 3, "subteamPlacement": 0, "summoner1Casts": 3, "summoner1Id": 4, "summoner2Casts": 3, "summoner2Id": 21, "summonerId": "SFbRrEx9Q4F1PorbkZIykwDEQYAUodqLMP1W86hpx2LQFw8", "summonerLevel": 1200, "summonerName": "", "teamEarlySurrendered": false, "teamId": 100, "teamPosition": "TOP", "timeCCingOthers": 9, "timePlayed": 1342, "totalAllyJungleMinionsKilled": 2, "totalDamageDealt": 134335, "totalDamageDealtToChampions": 16262, "totalDamageShieldedOnTeammates": 0, "totalDamageTaken": 18631, "totalEnemyJungleMinionsKilled": 0, "totalHeal": 6558, "totalHealsOnTeammates": 0, "totalMinionsKilled": 204, "totalTimeCCDealt": 265, "totalTimeSpentDead": 103, "totalUnitsHealed": 1, "tripleKills": 1, "trueDamageDealt": 5102, "trueDamageDealtToChampions": 820, "trueDamageTaken": 92, "turretKills": 3, "turretTakedowns": 4, "turretsLost": 1, "unrealKills": 0, "visionClearedPings": 0, "visionScore": 23, "visionWardsBoughtInGame": 0, "wardsKilled": 2, "wardsPlaced": 8, "win": true}, {"PlayerBehavior": {"PlayerBehavior_IsHeroInCombat": 0}, "PlayerScore0": 0, "PlayerScore1": 0, "PlayerScore10": 0, "PlayerScore11": 0, "PlayerScore2": 0, "PlayerScore3": 0, "PlayerScore4": 0, "PlayerScore5": 0, "PlayerScore6": 0, "PlayerScore7": 0, "PlayerScore8": 0, "PlayerScore9": 0, "allInPings": 0, "assistMePings": 3, "assists": 15, "baronKills": 1, "basicPings": 0, "challenges": {"12AssistStreakCount": 0, "HealFromMapSources": 80, "InfernalScalePickup": 0, "SWARM_DefeatAatrox": 0, "SWARM_DefeatBriar": 0, "SWARM_DefeatMiniBosses": 0, "SWARM_EvolveWeapon": 0, "SWARM_Have3Passives": 0, "SWARM_KillEnemy": 0, "SWARM_PickupGold": 0, "SWARM_ReachLevel50": 0, "SWARM_Survive15Min": 0, "SWARM_WinWith5EvolvedWeapons": 0, "abilityUses": 270, "acesBefore15Minutes": 0, "alliedJungleMonsterKills": 58, "baronBuffGoldAdvantageOverThreshold": 1, "baronTakedowns": 1, "blastConeOppositeOpponentCount": 0, "bountyGold": 0, "buffsStolen": 2, "completeSupportQuestInTime": 0, "controlWardTimeCoverageInRiverOrEnemyHalf": 0.7572396989115404, "controlWardsPlaced": 4, "damagePerMinute": 476.05836952451523, "damageTakenOnTeamPercentage": 0.21667248635755584, "dancedWithRiftHerald": 0, "deathsByEnemyChamps": 4, "dodgeSkillShotsSmallWindow": 0, "doubleAces": 0, "dragonTakedowns": 2, "earliestBaron": 1228.0247327480001, "earliestDragonTakedown": 616.890835626, "earlyLaningPhaseGoldExpAdvantage": 0, "effectiveHealAndShielding": 0, "elderDragonKillsWithOpposingSoul": 0, "elderDragonMultikills": 0, "enemyChampionImmobilizations": 2, "enemyJungleMonsterKills": 11, "epicMonsterKillsNearEnemyJungler": 1, "epicMonsterKillsWithin30SecondsOfSpawn": 1, "epicMonsterSteals": 0, "epicMonsterStolenWithoutSmite": 0, "firstTurretKilled": 1, "firstTurretKilledTime": 708.630564453, "fistBumpParticipation": 0, "flawlessAces": 1, "fullTeamTakedown": 1, "gameLength": 1342.98021752, "goldPerMinute": 433.67291120677027, "hadOpenNexus": 0, "immobilizeAndKillWithAlly": 1, "initialBuffCount": 2, "initialCrabCount": 0, "jungleCsBefore10Minutes": 48.000000059604645, "junglerKillsEarlyJungle": 0, "junglerTakedownsNearDamagedEpicMonster": 0, "kTurretsDestroyedBeforePlatesFall": 0, "kda": 4.5, "killAfterHiddenWithAlly": 0, "killParticipation": 0.6923076923076923, "killedChampTookFullTeamDamageSurvived": 0, "killingSprees": 0, "killsNearEnemyTurret": 0, "killsOnLanersEarlyJungleAsJungler": 2, "killsOnRecentlyHealedByAramPack": 0, "killsUnderOwnTurret": 0, "killsWithHelpFromEpicMonster": 0, "knockEnemyIntoTeamAndKill": 0, "landSkillShotsEarlyGame": 0, "laneMinionsFirst10Minutes": 2, "laningPhaseGoldExpAdvantage": 0, "legendaryCount": 0, "legendaryItemUsed": [6698, 6695, 6696], "lostAnInhibitor": 0, "maxCsAdvantageOnLaneOpponent": 4, "maxKillDeficit": 1, "maxLevelLeadLaneOpponent": 1, "mejaisFullStackInTime": 0, "moreEnemyJungleThanOpponent": -57.00000011920929, "multiKillOneSpell": 0, "multiTurretRiftHeraldCount": 0, "multikills": 1, "multikillsAfterAggressiveFlash": 0, "outerTurretExecutesBefore10Minutes": 0, "outnumberedKills": 1, "outnumberedNexusKill": 0, "perfectDragonSoulsTaken": 0, "perfectGame": 0, "pickKillWithAlly": 15, "playedChampSelectPosition": 1, "poroExplosions": 0, "quickCleanse": 0, "quickFirstTurret": 0, "quickSoloKills": 0, "riftHeraldTakedowns": 1, "saveAllyFromDeath": 0, "scuttleCrabKills": 2, "skillshotsDodged": 7, "skillshotsHit": 0, "snowballsHit": 0, "soloBaronKills": 0, "soloKills": 0, "stealthWardsPlaced": 3, "survivedSingleDigitHpCount": 0, "survivedThreeImmobilizesInFight": 0, "takedownOnFirstTurret": 0, "takedowns": 18, "takedownsAfterGainingLevelAdvantage": 0, "takedownsBeforeJungleMinionSpawn": 0, "takedownsFirstXMinutes": 11, "takedownsInAlcove": 0, "takedownsInEnemyFountain": 0, "teamBaronKills": 1, "teamDamagePercentage": 0.13791487456406726, "teamElderDragonKills": 0, "teamRiftHeraldKills": 1, "tookLargeDamageSurvived": 0, "turretPlatesTaken": 15, "turretTakedowns": 4, "turretsTakenWithRiftHerald": 0, "twentyMinionsIn3SecondsCount": 0, "twoWardsOneSweeperCount": 0, "unseenRecalls": 0, "visionScoreAdvantageLaneOpponent": 0.20990407466888428, "visionScorePerMinute": 1.2553026843323545, "voidMonsterKill": 2, "wardTakedowns": 6, "wardTakedownsBefore20M": 5, "wardsGuarded": 1}, "champExperience": 10581, "champLevel": 13, "championId": 59, "championName": "JarvanIV", "championTransform": 0, "commandPings": 14, "consumablesPurchased": 6, "damageDealtToBuildings": 9124, "damageDealtToEpicMonsters": 30791, "damageDealtToObjectives": 39915, "damageDealtToTurrets": 9124, "damageSelfMitigated": 19886, "dangerPings": 0, "deaths": 4, "detectorWardsPlaced": 4, "doubleKills": 1, "dragonKills": 2, "eligibleForProgression": true, "enemyMissingPings": 17, "enemyVisionPings": 9, "firstBloodAssist": true, "firstBloodKill": false, "firstTowerAssist": false, "firstTowerKill": false, "gameEndedInEarlySurrender": false, "gameEndedInSurrender": true, "getBackPings": 6, "goldEarned": 9706, "goldSpent": 9300, "holdPings": 0, "individualPosition": "JUNGLE", "inhibitorKills": 0, "inhibitorTakedowns": 0, "inhibitorsLost": 0, "item0": 6695, "item1": 6698, "item2": 6696, "item3": 1028, "item4": 0, "item5": 2422, "item6": 3364, "itemsPurchased": 22, "killingSprees": 1, "kills": 3, "lane": "JUNGLE", "largestCriticalStrike": 0, "largestKillingSpree": 2, "largestMultiKill": 2, "longestTimeSpentLiving": 739, "magicDamageDealt": 6210, "magicDamageDealtToChampions": 676, "magicDamageTaken": 3389, "missions": {"playerScore0": 0, "playerScore1": 0, "playerScore2": 0, "playerScore3": 0, "playerScore4": 0, "playerScore5": 0, "playerScore6": 0, "playerScore7": 0, "playerScore8": 0, "playerScore9": 0, "playerScore10": 0, "playerScore11": 0}, "needVisionPings": 1, "neutralMinionsKilled": 128, "nexusKills": 0, "nexusLost": 0, "nexusTakedowns": 0, "objectivesStolen": 0, "objectivesStolenAssists": 0, "onMyWayPings": 40, "participantId": 2, "pentaKills": 0, "perks": {"statPerks": {"defense": 5011, "flex": 5008, "offense": 5005}, "styles": [{"description": "primaryStyle", "selections": [{"perk": 8010, "var1": 125, "var2": 0, "var3": 0}, {"perk": 9111, "var1": 875, "var2": 360, "var3": 0}, {"perk": 9104, "var1": 7, "var2": 50, "var3": 0}, {"perk": 8014, "var1": 339, "var2": 0, "var3": 0}], "style": 8000}, {"description": "subStyle", "selections": [{"perk": 8347, "var1": 0, "var2": 0, "var3": 0}, {"perk": 8304, "var1": 7, "var2": 3, "var3": 0}], "style": 8300}]}, "physicalDamageDealt": 112438, "physicalDamageDealtToChampions": 9573, "physicalDamageTaken": 10904, "placement": 0, "playerAugment1": 0, "playerAugment2": 0, "playerAugment3": 0, "playerAugment4": 0, "playerAugment5": 0, "playerAugment6": 0, "playerSubteamId": 0, "profileIcon": 1438, "pushPings": 0, "puuid": "MstO4vI4ZxH5lFz0BAzR4DioM00Evm0yfhTewKJh-_VXxMLAa67pFg9aynNHd5mUPC0T8bRU9scJcw", "quadraKills": 0, "retreatPings": 7, "riotIdGameName": "건강하세요", "riotIdTagline": "123", "role": "NONE", "roleBoundItem": 1209, "sightWardsBoughtInGame": 0, "spell1Casts": 106, "spell2Casts": 63, "spell3Casts": 92, "spell4Casts": 9, "subteamPlacement": 0, "summoner1Casts": 2, "summoner1Id": 4, "summoner2Casts": 15, "summoner2Id": 11, "summonerId": "MMre4hpsE3-8nLVS1r_zDu_nsUbx_HbYVVbyyW2iQqUsucoFhRr9w5ECbA", "summonerLevel": 812, "summonerName": "", "teamEarlySurrendered": false, "teamId": 100, "teamPosition": "JUNGLE", "timeCCingOthers": 9, "timePlayed": 1342, "totalAllyJungleMinionsKilled": 78, "totalDamageDealt": 182359, "totalDamageDealtToChampions": 10655, "totalDamageShieldedOnTeammates": 0, "totalDamageTaken": 14375, "totalEnemyJungleMinionsKilled": 18, "totalHeal": 6081, "totalHealsOnTeammates": 0, "totalMinionsKilled": 8, "totalTimeCCDealt": 327, "totalTimeSpentDead": 79, "totalUnitsHealed": 1, "tripleKills": 0, "trueDamageDealt": 63711, "trueDamageDealtToChampions": 406, "trueDamageTaken": 81, "turretKills": 1, "turretTakedowns": 4, "turretsLost": 1, "unrealKills": 0, "visionClearedPings": 0, "visionScore": 28, "visionWardsBoughtInGame": 4, "wardsKilled": 6, "wardsPlaced": 7, "win": true}, {"PlayerBehavior": {"PlayerBehavior_IsHeroInCombat": 0}, "PlayerScore0": 0, "PlayerScore1": 0, "PlayerScore10": 0, "PlayerScore11": 0, "PlayerScore2": 0, "PlayerScore3": 0, "PlayerScore4": 0, "PlayerScore5": 0, "PlayerScore6": 0, "PlayerScore7": 0, "PlayerScore8": 0, "PlayerScore9": 0, "allInPings": 0, "assistMePings": 25, "assists": 9, "baronKills": 0, "basicPings": 0, "challenges": {"12AssistStreakCount": 0, "HealFromMapSources": 0, "InfernalScalePickup": 0, "SWARM_DefeatAatrox": 0, "SWARM_DefeatBriar": 0, "SWARM_DefeatMiniBosses": 0, "SWARM_EvolveWeapon": 0, "SWARM_Have3Passives": 0, "SWARM_KillEnemy": 0, "SWARM_PickupGold": 0, "SWARM_ReachLevel50": 0, "SWARM_Survive15Min": 0, "SWARM_WinWith5EvolvedWeapons": 0, "abilityUses": 290, "acesBefore15Minutes": 0, "alliedJungleMonsterKills": 0, "baronBuffGoldAdvantageOverThreshold": 1, "baronTakedowns": 1, "blastConeOppositeOpponentCount": 0, "bountyGold": 0, "buffsStolen": 0, "completeSupportQuestInTime": 0, "controlWardTimeCoverageInRiverOrEnemyHalf": 0.7368064827792326, "controlWardsPlaced": 3, "damagePerMinute": 822.1551960768602, "damageTakenOnTeamPercentage": 0.17906729384403092, "dancedWithRiftHerald": 0, "deathsByEnemyChamps": 4, "dodgeSkillShotsSmallWindow": 0, "doubleAces": 0, "dragonTakedowns": 0, "earliestBaron": 1228.0247327480001, "earlyLaningPhaseGoldExpAdvantage": 0, "effectiveHealAndShielding": 1426.525634765625, "elderDragonKillsWithOpposingSoul": 0, "elderDragonMultikills": 0, "enemyChampionImmobilizations": 12, "enemyJungleMonsterKills": 0, "epicMonsterKillsNearEnemyJungler": 0, "epicMonsterKillsWithin30SecondsOfSpawn": 0, "epicMonsterSteals": 0, "epicMonsterStolenWithoutSmite": 0, "firstTurretKilled": 1, "firstTurretKilledTime": 708.630564453, "fistBumpParticipation": 0, "flawlessAces": 1, "fullTeamTakedown": 1, "gameLength": 1342.98021752, "getTakedownsInAllLanesEarlyJungleAsLaner": 0, "goldPerMinute": 420.15369854868834, "hadOpenNexus": 0, "immobilizeAndKillWithAlly": 3, "initialBuffCount": 0, "initialCrabCount": 0, "jungleCsBefore10Minutes": 0, "junglerTakedownsNearDamagedEpicMonster": 0, "kTurretsDestroyedBeforePlatesFall": 0, "kda": 3, "killAfterHiddenWithAlly": 3, "killParticipation": 0.46153846153846156, "killedChampTookFullTeamDamageSurvived": 0, "killingSprees": 1, "killsNearEnemyTurret": 2, "killsOnOtherLanesEarlyJungleAsLaner": 0, "killsOnRecentlyHealedByAramPack": 0, "killsUnderOwnTurret": 0, "killsWithHelpFromEpicMonster": 0, "knockEnemyIntoTeamAndKill": 3, "landSkillShotsEarlyGame": 11, "laneMinionsFirst10Minutes": 100, "laningPhaseGoldExpAdvantage": 0, "legendaryCount": 0, "legendaryItemUsed": [6655, 4646], "lostAnInhibitor": 0, "maxCsAdvantageOnLaneOpponent": 33, "maxKillDeficit": 1, "maxLevelLeadLaneOpponent": 2, "mejaisFullStackInTime": 0, "moreEnemyJungleThanOpponent": 0, "multiKillOneSpell": 0, "multiTurretRiftHeraldCount": 0, "multikills": 0, "multikillsAfterAggressiveFlash": 0, "outerTurretExecutesBefore10Minutes": 0, "outnumberedKills": 0, "outnumberedNexusKill": 0, "perfectDragonSoulsTaken": 0, "perfectGame": 0, "pickKillWithAlly": 9, "playedChampSelectPosition": 1, "poroExplosions": 0, "quickCleanse": 0, "quickFirstTurret": 0, "quickSoloKills": 0, "riftHeraldTakedowns": 0, "saveAllyFromDeath": 0, "scuttleCrabKills": 1, "skillshotsDodged": 2, "skillshotsHit": 44, "snowballsHit": 0, "soloBaronKills": 0, "soloKills": 0, "stealthWardsPlaced": 4, "survivedSingleDigitHpCount": 0, "survivedThreeImmobilizesInFight": 0, "takedownOnFirstTurret": 0, "takedowns": 12, "takedownsAfterGainingLevelAdvantage": 0, "takedownsBeforeJungleMinionSpawn": 0, "takedownsFirstXMinutes": 4, "takedownsInAlcove": 0, "takedownsInEnemyFountain": 0, "teamBaronKills": 1, "teamDamagePercentage": 0.2381796813117415, "teamElderDragonKills": 0, "teamRiftHeraldKills": 1, "tookLargeDamageSurvived": 0, "turretPlatesTaken": 14, "turretTakedowns": 4, "turretsTakenWithRiftHerald": 0, "twentyMinionsIn3SecondsCount": 0, "twoWardsOneSweeperCount": 0, "unseenRecalls": 0, "visionScoreAdvantageLaneOpponent": 0.14969134330749512, "visionScorePerMinute": 1.4248564319049584, "voidMonsterKill": 2, "wardTakedowns": 6, "wardTakedownsBefore20M": 3, "wardsGuarded": 1}, "champExperience": 12495, "champLevel": 14, "championId": 61, "championName": "Orianna", "championTransform": 0, "commandPings": 24, "consumablesPurchased": 6, "damageDealtToBuildings": 4692, "damageDealtToEpicMonsters": 759, "damageDealtToObjectives": 5451, "damageDealtToTurrets": 4692, "damageSelfMitigated": 7279, "dangerPings": 0, "deaths": 4, "detectorWardsPlaced": 3, "doubleKills": 0, "dragonKills": 0, "eligibleForProgression": true, "enemyMissingPings": 13, "enemyVisionPings": 1, "firstBloodAssist": false, "firstBloodKill": false, "firstTowerAssist": false, "firstTowerKill": false, "gameEndedInEarlySurrender": false, "gameEndedInSurrender": true, "getBackPings": 0, "goldEarned": 9404, "goldSpent": 8000, "holdPings": 0, "individualPosition": "MIDDLE", "inhibitorKills": 0, "inhibitorTakedowns": 0, "inhibitorsLost": 0, "item0": 1082, "item1": 6655, "item2": 4646, "item3": 3171, "item4": 1052, "item5": 1056, "item6": 3363, "itemsPurchased": 23, "killingSprees": 1, "kills": 3, "lane": "MIDDLE", "largestCriticalStrike": 0, "largestKillingSpree": 3, "largestMultiKill": 1, "longestTimeSpentLiving": 377, "magicDamageDealt": 97677, "magicDamageDealtToChampions": 17583, "magicDamageTaken": 6428, "missions": {"playerScore0": 0, "playerScore1": 0, "playerScore2": 0, "playerScore3": 0, "playerScore4": 0, "playerScore5": 0, "playerScore6": 0, "playerScore7": 0, "playerScore8": 0, "playerScore9": 0, "playerScore10": 0, "playerScore11": 0}, "needVisionPings": 0, "neutralMinionsKilled": 4, "nexusKills": 0, "nexusLost": 0, "nexusTakedowns": 0, "objectivesStolen": 0, "objectivesStolenAssists": 0, "onMyWayPings": 32, "participantId": 3, "pentaKills": 0, "perks": {"statPerks": {"defense": 5011, "flex": 5010, "offense": 5005}, "styles": [{"description": "primaryStyle", "selections": [{"perk": 8214, "var1": 957, "var2": 334, "var3": 0}, {"perk": 8226, "var1": 250, "var2": 961, "var3": 0}, {"perk": 8210, "var1": 7, "var2": 0, "var3": 0}, {"perk": 8237, "var1": 514, "var2": 0, "var3": 0}], "style": 8200}, {"description": "subStyle", "selections": [{"perk": 8017, "var1": 990, "var2": 0, "var3": 0}, {"perk": 9105, "var1": 16, "var2": 50, "var3": 0}], "style": 8000}]}, "physicalDamageDealt": 12111, "physicalDamageDealtToChampions": 818, "physicalDamageTaken": 5311, "placement": 0, "playerAugment1": 0, "playerAugment2": 0, "playerAugment3": 0, "playerAugment4": 0, "playerAugment5": 0, "playerAugment6": 0, "playerSubteamId": 0, "profileIcon": 4561, "pushPings": 0, "puuid": "I4SKg4yOf9T5TvsvDoql-pBh7mk2yph6ne2fT1nFWL9Bvvfy9sjcKuSai-fuxHH-xz0gEXhUyT0INw", "quadraKills": 0, "retreatPings": 6, "riotIdGameName": "mashushu", "riotIdTagline": "KR1", "role": "SOLO", "roleBoundItem": 1206, "sightWardsBoughtInGame": 0, "spell1Casts": 150, "spell2Casts": 90, "spell3Casts": 43, "spell4Casts": 7, "subteamPlacement": 0, "summoner1Casts": 3, "summoner1Id": 4, "summoner2Casts": 4, "summoner2Id": 12, "summonerId": "EhHfTYfrDKyt8QI3zsgs0HNk28i9GVpXvESBi3PDVJLPEMND0M-5ijinqw", "summonerLevel": 317, "summonerName": "", "teamEarlySurrendered": false, "teamId": 100, "teamPosition": "MIDDLE", "timeCCingOthers": 21, "timePlayed": 1342, "totalAllyJungleMinionsKilled": 0, "totalDamageDealt": 111319, "totalDamageDealtToChampions": 18402, "totalDamageShieldedOnTeammates": 1426, "totalDamageTaken": 11880, "totalEnemyJungleMinionsKilled": 0, "totalHeal": 1465, "totalHealsOnTeammates": 0, "totalMinionsKilled": 195, "totalTimeCCDealt": 279, "totalTimeSpentDead": 116, "totalUnitsHealed": 1, "tripleKills": 0, "trueDamageDealt": 1530, "trueDamageDealtToChampions": 0, "trueDamageTaken": 139, "turretKills": 1, "turretTakedowns": 4, "turretsLost": 1, "unrealKills": 0, "visionClearedPings": 0, "visionScore": 31, "visionWardsBoughtInGame": 4, "wardsKilled": 6, "wardsPlaced": 10, "win": true}, {"PlayerBehavior": {"PlayerBehavior_IsHeroInCombat": 0}, "PlayerScore0": 0, "PlayerScore1": 0, "PlayerScore10": 0, "PlayerScore11": 0, "PlayerScore2": 0, "PlayerScore3": 0, "PlayerScore4": 0, "PlayerScore5": 0, "PlayerScore6": 0, "PlayerScore7": 0, "PlayerScore8": 0, "PlayerScore9": 0, "allInPings": 10, "assistMePings": 2, "assists": 9, "baronKills": 0, "basicPings": 0, "challenges": {"12AssistStreakCount": 0, "HealFromMapSources": 106, "InfernalScalePickup": 0, "SWARM_DefeatAatrox": 0, "SWARM_DefeatBriar": 0, "SWARM_DefeatMiniBosses": 0, "SWARM_EvolveWeapon": 0, "SWARM_Have3Passives": 0, "SWARM_KillEnemy": 0, "SWARM_PickupGold": 0, "SWARM_ReachLevel50": 0, "SWARM_Survive15Min": 0, "SWARM_WinWith5EvolvedWeapons": 0, "abilityUses": 138, "acesBefore15Minutes": 0, "alliedJungleMonsterKills": 1, "baronBuffGoldAdvantageOverThreshold": 1, "baronTakedowns": 1, "blastConeOppositeOpponentCount": 0, "bountyGold": 0, "buffsStolen": 0, "completeSupportQuestInTime": 0, "controlWardTimeCoverageInRiverOrEnemyHalf": 0.21953343005337997, "controlWardsPlaced": 3, "damagePerMinute": 971.2435390773544, "damageTakenOnTeamPercentage": 0.16390409328006528, "dancedWithRiftHerald": 0, "deathsByEnemyChamps": 1, "dodgeSkillShotsSmallWindow": 0, "doubleAces": 0, "dragonTakedowns": 0, "earliestBaron": 1228.0247327480001, "earlyLaningPhaseGoldExpAdvantage": 0, "effectiveHealAndShielding": 0, "elderDragonKillsWithOpposingSoul": 0, "elderDragonMultikills": 0, "enemyChampionImmobilizations": 0, "enemyJungleMonsterKills": 5, "epicMonsterKillsNearEnemyJungler": 0, "epicMonsterKillsWithin30SecondsOfSpawn": 0, "epicMonsterSteals": 0, "epicMonsterStolenWithoutSmite": 0, "firstTurretKilled": 1, "firstTurretKilledTime": 708.630564453, "fistBumpParticipation": 0, "flawlessAces": 1, "fullTeamTakedown": 1, "gameLength": 1342.98021752, "getTakedownsInAllLanesEarlyJungleAsLaner": 0, "goldPerMinute": 586.0628403258879, "hadOpenNexus": 0, "highestChampionDamage": 1, "immobilizeAndKillWithAlly": 0, "initialBuffCount": 0, "initialCrabCount": 0, "jungleCsBefore10Minutes": 0, "junglerTakedownsNearDamagedEpicMonster": 0, "kTurretsDestroyedBeforePlatesFall": 1, "kda": 15, "killAfterHiddenWithAlly": 3, "killParticipation": 0.5769230769230769, "killedChampTookFullTeamDamageSurvived": 0, "killingSprees": 1, "killsNearEnemyTurret": 2, "killsOnOtherLanesEarlyJungleAsLaner": 0, "killsOnRecentlyHealedByAramPack": 0, "killsUnderOwnTurret": 0, "killsWithHelpFromEpicMonster": 0, "knockEnemyIntoTeamAndKill": 0, "landSkillShotsEarlyGame": 8, "laneMinionsFirst10Minutes": 97, "laningPhaseGoldExpAdvantage": 0, "legendaryCount": 0, "legendaryItemUsed": [6672, 2512, 3031], "lostAnInhibitor": 0, "maxCsAdvantageOnLaneOpponent": 53, "maxKillDeficit": 1, "maxLevelLeadLaneOpponent": 2, "mejaisFullStackInTime": 0, "moreEnemyJungleThanOpponent": 0, "multiKillOneSpell": 0, "multiTurretRiftHeraldCount": 0, "multikills": 0, "multikillsAfterAggressiveFlash": 0, "outerTurretExecutesBefore10Minutes": 0, "outnumberedKills": 0, "outnumberedNexusKill": 0, "perfectDragonSoulsTaken": 0, "perfectGame": 0, "pickKillWithAlly": 12, "playedChampSelectPosition": 1, "poroExplosions": 0, "quickCleanse": 0, "quickFirstTurret": 0, "quickSoloKills": 0, "riftHeraldTakedowns": 1, "saveAllyFromDeath": 0, "scuttleCrabKills": 0, "skillshotsDodged": 11, "skillshotsHit": 25, "snowballsHit": 0, "soloBaronKills": 0, "soloKills": 0, "stealthWardsPlaced": 4, "survivedSingleDigitHpCount": 0, "survivedThreeImmobilizesInFight": 1, "takedownOnFirstTurret": 1, "takedowns": 15, "takedownsAfterGainingLevelAdvantage": 1, "takedownsBeforeJungleMinionSpawn": 0, "takedownsFirstXMinutes": 9, "takedownsInAlcove": 0, "takedownsInEnemyFountain": 0, "teamBaronKills": 1, "teamDamagePercentage": 0.2813708138285682, "teamElderDragonKills": 0, "teamRiftHeraldKills": 1, "tookLargeDamageSurvived": 0, "turretPlatesTaken": 17, "turretTakedowns": 5, "turretsTakenWithRiftHerald": 0, "twentyMinionsIn3SecondsCount": 0, "twoWardsOneSweeperCount": 0, "unseenRecalls": 0, "visionScoreAdvantageLaneOpponent": 0.3042484521865845, "visionScorePerMinute": 0.9152364447832686, "voidMonsterKill": 2, "wardTakedowns": 4, "wardTakedownsBefore20M": 3, "wardsGuarded": 0}, "champExperience": 10180, "champLevel": 13, "championId": 804, "championName": "Yunara", "championTransform": 0, "commandPings": 8, "consumablesPurchased": 5, "damageDealtToBuildings": 10320, "damageDealtToEpicMonsters": 7999, "damageDealtToObjectives": 18319, "damageDealtToTurrets": 10320, "damageSelfMitigated": 7588, "dangerPings": 0, "deaths": 1, "detectorWardsPlaced": 3, "doubleKills": 0, "dragonKills": 0, "eligibleForProgression": true, "enemyMissingPings": 15, "enemyVisionPings": 24, "firstBloodAssist": true, "firstBloodKill": false, "firstTowerAssist": false, "firstTowerKill": true, "gameEndedInEarlySurrender": false, "gameEndedInSurrender": true, "getBackPings": 2, "goldEarned": 13117, "goldSpent": 12375, "holdPings": 0, "individualPosition": "BOTTOM", "inhibitorKills": 0, "inhibitorTakedowns": 0, "inhibitorsLost": 0, "item0": 1055, "item1": 3123, "item2": 0, "item3": 2512, "item4": 3031, "item5": 6672, "item6": 3363, "itemsPurchased": 26, "killingSprees": 2, "kills": 6, "lane": "BOTTOM", "largestCriticalStrike": 563, "largestKillingSpree": 4, "largestMultiKill": 1, "longestTimeSpentLiving": 813, "magicDamageDealt": 38688, "magicDamageDealtToChampions": 9094, "magicDamageTaken": 3853, "missions": {"playerScore0": 0, "playerScore1": 0, "playerScore2": 0, "playerScore3": 0, "playerScore4": 0, "playerScore5": 0, "playerScore6": 0, "playerScore7": 0, "playerScore8": 0, "playerScore9": 0, "playerScore10": 0, "playerScore11": 0}, "needVisionPings": 0, "neutralMinionsKilled": 7, "nexusKills": 0, "nexusLost": 0, "nexusTakedowns": 0, "objectivesStolen": 0, "objectivesStolenAssists": 0, "onMyWayPings": 22, "participantId": 4, "pentaKills": 0, "perks": {"statPerks": {"defense": 5011, "flex": 5008, "offense": 5005}, "styles": [{"description": "primaryStyle", "selections": [{"perk": 8008, "var1": 390, "var2": 390, "var3": 0}, {"perk": 9111, "var1": 765, "var2": 300, "var3": 0}, {"perk": 9103, "var1": 15, "var2": 20, "var3": 0}, {"perk": 8017, "var1": 991, "var2": 0, "var3": 0}], "style": 8000}, {"description": "subStyle", "selections": [{"perk": 8321, "var1": 686, "var2": 0, "var3": 0}, {"perk": 8313, "var1": 3, "var2": 0, "var3": 0}], "style": 8300}]}, "physicalDamageDealt": 86463, "physicalDamageDealtToChampions": 12313, "physicalDamageTaken": 6654, "placement": 0, "playerAugment1": 0, "playerAugment2": 0, "playerAugment3": 0, "playerAugment4": 0, "playerAugment5": 0, "playerAugment6": 0, "playerSubteamId": 0, "profileIcon": 7, "pushPings": 5, "puuid": "eNFqceGnXYoJgGaQcS7871WgiazFI_aGhMfPJ8dz_xVScadobkwnfFl72xR0zZpPTFJK8uYGGLALrQ", "quadraKills": 0, "retreatPings": 0, "riotIdGameName": "HealthandAhn", "riotIdTagline": "Ahn", "role": "CARRY", "roleBoundItem": 3047, "sightWardsBoughtInGame": 0, "spell1Casts": 25, "spell2Casts": 59, "spell3Casts": 47, "spell4Casts": 7, "subteamPlacement": 0, "summoner1Casts": 1, "summoner1Id": 21, "summoner2Casts": 3, "summoner2Id": 4, "summonerId": "MPLEGIe1DsG2vP_tc5qIV3NFfrG8Aw7VAVv2u9V4l5XYEh-NQK_mA_JwWA", "summonerLevel": 170, "summonerName": "", "teamEarlySurrendered": false, "teamId": 100, "teamPosition": "BOTTOM", "timeCCingOthers": 8, "timePlayed": 1342, "totalAllyJungleMinionsKilled": 4, "totalDamageDealt": 129936, "totalDamageDealtToChampions": 21739, "totalDamageShieldedOnTeammates": 0, "totalDamageTaken": 10874, "totalEnemyJungleMinionsKilled": 3, "totalHeal": 4784, "totalHealsOnTeammates": 0, "totalMinionsKilled": 210, "totalTimeCCDealt": 165, "totalTimeSpentDead": 28, "totalUnitsHealed": 1, "tripleKills": 0, "trueDamageDealt": 4784, "trueDamageDealtToChampions": 332, "trueDamageTaken": 366, "turretKills": 2, "turretTakedowns": 5, "turretsLost": 1, "unrealKills": 0, "visionClearedPings": 0, "visionScore": 20, "visionWardsBoughtInGame": 3, "wardsKilled": 4, "wardsPlaced": 9, "win": true}, {"PlayerBehavior": {"PlayerBehavior_IsHeroInCombat": 0}, "PlayerScore0": 0, "PlayerScore1": 0, "PlayerScore10": 0, "PlayerScore11": 0, "PlayerScore2": 0, "PlayerScore3": 0, "PlayerScore4": 0, "PlayerScore5": 0, "PlayerScore6": 0, "PlayerScore7": 0, "PlayerScore8": 0, "PlayerScore9": 0, "allInPings": 0, "assistMePings": 4, "assists": 16, "baronKills": 0, "basicPings": 0, "challenges": {"12AssistStreakCount": 0, "HealFromMapSources": 0, "InfernalScalePickup": 0, "SWARM_DefeatAatrox": 0, "SWARM_DefeatBriar": 0, "SWARM_DefeatMiniBosses": 0, "SWARM_EvolveWeapon": 0, "SWARM_Have3Passives": 0, "SWARM_KillEnemy": 0, "SWARM_PickupGold": 0, "SWARM_ReachLevel50": 0, "SWARM_Survive15Min": 0, "SWARM_WinWith5EvolvedWeapons": 0, "abilityUses": 184, "acesBefore15Minutes": 0, "alliedJungleMonsterKills": 0, "baronBuffGoldAdvantageOverThreshold": 1, "baronTakedowns": 1, "blastConeOppositeOpponentCount": 0, "bountyGold": 0, "buffsStolen": 0, "completeSupportQuestInTime": 1, "controlWardTimeCoverageInRiverOrEnemyHalf": 0.8497469794948824, "controlWardsPlaced": 9, "damagePerMinute": 455.7955408022487, "damageTakenOnTeamPercentage": 0.1595376986515043, "dancedWithRiftHerald": 0, "deathsByEnemyChamps": 1, "dodgeSkillShotsSmallWindow": 0, "doubleAces": 0, "dragonTakedowns": 0, "earliestBaron": 1228.0247327480001, "earlyLaningPhaseGoldExpAdvantage": 0, "effectiveHealAndShielding": 3411.925048828125, "elderDragonKillsWithOpposingSoul": 0, "elderDragonMultikills": 0, "enemyChampionImmobilizations": 10, "enemyJungleMonsterKills": 1, "epicMonsterKillsNearEnemyJungler": 0, "epicMonsterKillsWithin30SecondsOfSpawn": 0, "epicMonsterSteals": 0, "epicMonsterStolenWithoutSmite": 0, "fasterSupportQuestCompletion": 1, "firstTurretKilled": 1, "firstTurretKilledTime": 708.630564453, "fistBumpParticipation": 0, "flawlessAces": 1, "fullTeamTakedown": 1, "gameLength": 1342.98021752, "getTakedownsInAllLanesEarlyJungleAsLaner": 0, "goldPerMinute": 352.8554293995532, "hadOpenNexus": 0, "highestWardKills": 1, "immobilizeAndKillWithAlly": 6, "initialBuffCount": 0, "initialCrabCount": 0, "jungleCsBefore10Minutes": 0, "junglerTakedownsNearDamagedEpicMonster": 0, "kTurretsDestroyedBeforePlatesFall": 0, "kda": 19, "killAfterHiddenWithAlly": 4, "killParticipation": 0.7307692307692307, "killedChampTookFullTeamDamageSurvived": 0, "killingSprees": 0, "killsNearEnemyTurret": 2, "killsOnOtherLanesEarlyJungleAsLaner": 0, "killsOnRecentlyHealedByAramPack": 0, "killsUnderOwnTurret": 0, "killsWithHelpFromEpicMonster": 0, "knockEnemyIntoTeamAndKill": 0, "landSkillShotsEarlyGame": 2, "laneMinionsFirst10Minutes": 14, "laningPhaseGoldExpAdvantage": 0, "legendaryCount": 0, "legendaryItemUsed": [3870, 6620, 3504], "lostAnInhibitor": 0, "maxCsAdvantageOnLaneOpponent": 0, "maxKillDeficit": 1, "maxLevelLeadLaneOpponent": 3, "mejaisFullStackInTime": 0, "moreEnemyJungleThanOpponent": 0, "multiKillOneSpell": 0, "multiTurretRiftHeraldCount": 0, "multikills": 0, "multikillsAfterAggressiveFlash": 0, "outerTurretExecutesBefore10Minutes": 0, "outnumberedKills": 0, "outnumberedNexusKill": 0, "perfectDragonSoulsTaken": 0, "perfectGame": 0, "pickKillWithAlly": 14, "playedChampSelectPosition": 1, "poroExplosions": 0, "quickCleanse": 0, "quickFirstTurret": 0, "quickSoloKills": 0, "riftHeraldTakedowns": 0, "saveAllyFromDeath": 0, "scuttleCrabKills": 0, "skillshotsDodged": 11, "skillshotsHit": 14, "snowballsHit": 0, "soloBaronKills": 0, "soloKills": 0, "stealthWardsPlaced": 21, "survivedSingleDigitHpCount": 0, "survivedThreeImmobilizesInFight": 1, "takedownOnFirstTurret": 0, "takedowns": 19, "takedownsAfterGainingLevelAdvantage": 0, "takedownsBeforeJungleMinionSpawn": 0, "takedownsFirstXMinutes": 8, "takedownsInAlcove": 0, "takedownsInEnemyFountain": 0, "teamBaronKills": 1, "teamDamagePercentage": 0.13204470052566994, "teamElderDragonKills": 0, "teamRiftHeraldKills": 1, "tookLargeDamageSurvived": 0, "turretPlatesTaken": 15, "turretTakedowns": 4, "turretsTakenWithRiftHerald": 0, "twentyMinionsIn3SecondsCount": 0, "twoWardsOneSweeperCount": 1, "unseenRecalls": 0, "visionScoreAdvantageLaneOpponent": 0.2346947193145752, "visionScorePerMinute": 3.3553995361867655, "voidMonsterKill": 1, "wardTakedowns": 9, "wardTakedownsBefore20M": 9, "wardsGuarded": 1}, "champExperience": 8576, "champLevel": 11, "championId": 43, "championName": "Karma", "championTransform": 0, "commandPings": 8, "consumablesPurchased": 12, "damageDealtToBuildings": 1153, "damageDealtToEpicMonsters": 0, "damageDealtToObjectives": 1153, "damageDealtToTurrets": 1153, "damageSelfMitigated": 6454, "dangerPings": 0, "deaths": 1, "detectorWardsPlaced": 9, "doubleKills": 0, "dragonKills": 0, "eligibleForProgression": true, "enemyMissingPings": 5, "enemyVisionPings": 11, "firstBloodAssist": false, "firstBloodKill": true, "firstTowerAssist": false, "firstTowerKill": false, "gameEndedInEarlySurrender": false, "gameEndedInSurrender": true, "getBackPings": 11, "goldEarned": 7897, "goldSpent": 6990, "holdPings": 0, "individualPosition": "UTILITY", "inhibitorKills": 0, "inhibitorTakedowns": 0, "inhibitorsLost": 0, "item0": 3916, "item1": 3870, "item2": 3504, "item3": 6620, "item4": 3158, "item5": 0, "item6": 3364, "itemsPurchased": 29, "killingSprees": 1, "kills": 3, "lane": "BOTTOM", "largestCriticalStrike": 0, "largestKillingSpree": 2, "largestMultiKill": 1, "longestTimeSpentLiving": 820, "magicDamageDealt": 18124, "magicDamageDealtToChampions": 8958, "magicDamageTaken": 4840, "missions": {"playerScore0": 0, "playerScore1": 0, "playerScore2": 0, "playerScore3": 0, "playerScore4": 0, "playerScore5": 0, "playerScore6": 0, "playerScore7": 0, "playerScore8": 0, "playerScore9": 0, "playerScore10": 0, "playerScore11": 0}, "needVisionPings": 0, "neutralMinionsKilled": 0, "nexusKills": 0, "nexusLost": 0, "nexusTakedowns": 0, "objectivesStolen": 0, "objectivesStolenAssists": 0, "onMyWayPings": 20, "participantId": 5, "pentaKills": 0, "perks": {"statPerks": {"defense": 5011, "flex": 5008, "offense": 5008}, "styles": [{"description": "primaryStyle", "selections": [{"perk": 8229, "var1": 852, "var2": 0, "var3": 0}, {"perk": 8275, "var1": 8, "var2": 0, "var3": 0}, {"perk": 8233, "var1": 18, "var2": 30, "var3": 0}, {"perk": 8237, "var1": 414, "var2": 0, "var3": 0}], "style": 8200}, {"description": "subStyle", "selections": [{"perk": 8304, "var1": 9, "var2": 0, "var3": 0}, {"perk": 8347, "var1": 0, "var2": 0, "var3": 0}], "style": 8300}]}, "physicalDamageDealt": 4115, "physicalDamageDealtToChampions": 1243, "physicalDamageTaken": 5744, "placement": 0, "playerAugment1": 0, "playerAugment2": 0, "playerAugment3": 0, "playerAugment4": 0, "playerAugment5": 0, "playerAugment6": 0, "playerSubteamId": 0, "profileIcon": 5952, "pushPings": 0, "puuid": "6jgyjL46WpaYXSxcgNp9_hZ5VqIcwYtKLCkwnY2TfrgTZOFLwhLZhy6yXPqG6BtTr89uRXIXpDd4FA", "quadraKills": 0, "retreatPings": 0, "riotIdGameName": "Loopy", "riotIdTagline": "1813", "role": "SUPPORT", "roleBoundItem": 1208, "sightWardsBoughtInGame": 0, "spell1Casts": 49, "spell2Casts": 23, "spell3Casts": 82, "spell4Casts": 30, "subteamPlacement": 0, "summoner1Casts": 4, "summoner1Id": 7, "summoner2Casts": 4, "summoner2Id": 4, "summonerId": "625LpVmp5tm_An5OBsY-Cza0hUV5tjKQ-k9ItW1uR-Qdgeo", "summonerLevel": 882, "summonerName": "", "teamEarlySurrendered": false, "teamId": 100, "teamPosition": "UTILITY", "timeCCingOthers": 23, "timePlayed": 1342, "totalAllyJungleMinionsKilled": 0, "totalDamageDealt": 23845, "totalDamageDealtToChampions": 10202, "totalDamageShieldedOnTeammates": 1653, "totalDamageTaken": 10584, "totalEnemyJungleMinionsKilled": 0, "totalHeal": 3815, "totalHealsOnTeammates": 1758, "totalMinionsKilled": 25, "totalTimeCCDealt": 119, "totalTimeSpentDead": 25, "totalUnitsHealed": 5, "tripleKills": 0, "trueDamageDealt": 1605, "trueDamageDealtToChampions": 0, "trueDamageTaken": 0, "turretKills": 0, "turretTakedowns": 4, "turretsLost": 1, "unrealKills": 0, "visionClearedPings": 0, "visionScore": 75, "visionWardsBoughtInGame": 5, "wardsKilled": 9, "wardsPlaced": 30, "win": true}, {"PlayerBehavior": {"PlayerBehavior_IsHeroInCombat": 0}, "PlayerScore0": 0, "PlayerScore1": 0, "PlayerScore10": 0, "PlayerScore11": 0, "PlayerScore2": 0, "PlayerScore3": 0, "PlayerScore4": 0, "PlayerScore5": 0, "PlayerScore6": 0, "PlayerScore7": 0, "PlayerScore8": 0, "PlayerScore9": 0, "allInPings": 0, "assistMePings": 4, "assists": 3, "baronKills": 0, "basicPings": 0, "challenges": {"12AssistStreakCount": 0, "HealFromMapSources": 62, "InfernalScalePickup": 0, "SWARM_DefeatAatrox": 0, "SWARM_DefeatBriar": 0, "SWARM_DefeatMiniBosses": 0, "SWARM_EvolveWeapon": 0, "SWARM_Have3Passives": 0, "SWARM_KillEnemy": 0, "SWARM_PickupGold": 0, "SWARM_ReachLevel50": 0, "SWARM_Survive15Min": 0, "SWARM_WinWith5EvolvedWeapons": 0, "abilityUses": 438, "acesBefore15Minutes": 0, "alliedJungleMonsterKills": 0, "baronTakedowns": 0, "blastConeOppositeOpponentCount": 0, "bountyGold": 0, "buffsStolen": 0, "completeSupportQuestInTime": 0, "controlWardTimeCoverageInRiverOrEnemyHalf": 0.43235178260945073, "controlWardsPlaced": 5, "damagePerMinute": 475.64253537895996, "damageTakenOnTeamPercentage": 0.14498598540810292, "dancedWithRiftHerald": 0, "deathsByEnemyChamps": 3, "dodgeSkillShotsSmallWindow": 0, "doubleAces": 0, "dragonTakedowns": 0, "earlyLaningPhaseGoldExpAdvantage": 1, "effectiveHealAndShielding": 7090.26513671875, "elderDragonKillsWithOpposingSoul": 0, "elderDragonMultikills": 0, "enemyChampionImmobilizations": 19, "enemyJungleMonsterKills": 0, "epicMonsterKillsNearEnemyJungler": 0, "epicMonsterKillsWithin30SecondsOfSpawn": 0, "epicMonsterSteals": 0, "epicMonsterStolenWithoutSmite": 0, "firstTurretKilled": 0, "fistBumpParticipation": 0, "flawlessAces": 0, "fullTeamTakedown": 0, "gameLength": 1342.98021752, "getTakedownsInAllLanesEarlyJungleAsLaner": 0, "goldPerMinute": 429.1361262113433, "hadOpenNexus": 0, "immobilizeAndKillWithAlly": 3, "initialBuffCount": 0, "initialCrabCount": 0, "jungleCsBefore10Minutes": 0, "junglerTakedownsNearDamagedEpicMonster": 0, "kTurretsDestroyedBeforePlatesFall": 1, "kda": 2.6666666666666665, "killAfterHiddenWithAlly": 0, "killParticipation": 0.5333333333333333, "killedChampTookFullTeamDamageSurvived": 0, "killingSprees": 1, "killsNearEnemyTurret": 0, "killsOnOtherLanesEarlyJungleAsLaner": 0, "killsOnRecentlyHealedByAramPack": 0, "killsUnderOwnTurret": 1, "killsWithHelpFromEpicMonster": 0, "knockEnemyIntoTeamAndKill": 0, "landSkillShotsEarlyGame": 2, "laneMinionsFirst10Minutes": 80, "laningPhaseGoldExpAdvantage": 1, "legendaryCount": 0, "legendaryItemUsed": [3118, 6620, 6617], "lostAnInhibitor": 0, "maxCsAdvantageOnLaneOpponent": 13, "maxKillDeficit": 0, "maxLevelLeadLaneOpponent": 3, "mejaisFullStackInTime": 0, "moreEnemyJungleThanOpponent": 0, "multiKillOneSpell": 0, "multiTurretRiftHeraldCount": 0, "multikills": 0, "multikillsAfterAggressiveFlash": 0, "outerTurretExecutesBefore10Minutes": 0, "outnumberedKills": 1, "outnumberedNexusKill": 0, "perfectDragonSoulsTaken": 0, "perfectGame": 0, "pickKillWithAlly": 5, "playedChampSelectPosition": 1, "poroExplosions": 0, "quickCleanse": 0, "quickFirstTurret": 0, "quickSoloKills": 0, "riftHeraldTakedowns": 0, "saveAllyFromDeath": 0, "scuttleCrabKills": 0, "skillshotsDodged": 4, "skillshotsHit": 9, "snowballsHit": 0, "soloBaronKills": 0, "soloKills": 2, "stealthWardsPlaced": 5, "survivedSingleDigitHpCount": 0, "survivedThreeImmobilizesInFight": 0, "takedownOnFirstTurret": 1, "takedowns": 8, "takedownsAfterGainingLevelAdvantage": 0, "takedownsBeforeJungleMinionSpawn": 0, "takedownsFirstXMinutes": 8, "takedownsInAlcove": 0, "takedownsInEnemyFountain": 0, "teamBaronKills": 0, "teamDamagePercentage": 0.23257131282023116, "teamElderDragonKills": 0, "teamRiftHeraldKills": 0, "tookLargeDamageSurvived": 0, "turretPlatesTaken": 9, "turretTakedowns": 1, "turretsTakenWithRiftHerald": 0, "twentyMinionsIn3SecondsCount": 0, "twoWardsOneSweeperCount": 0, "unseenRecalls": 0, "visionScoreAdvantageLaneOpponent": 0.2518796920776367, "visionScorePerMinute": 1.3413362537987021, "voidMonsterKill": 3, "wardTakedowns": 1, "wardTakedownsBefore20M": 0, "wardsGuarded": 0}, "champExperience": 12400, "champLevel": 14, "championId": 427, "championName": "Ivern", "championTransform": 0, "commandPings": 1, "consumablesPurchased": 7, "damageDealtToBuildings": 7143, "damageDealtToEpicMonsters": 642, "damageDealtToObjectives": 7785, "damageDealtToTurrets": 7143, "damageSelfMitigated": 17081, "dangerPings": 0, "deaths": 3, "detectorWardsPlaced": 5, "doubleKills": 0, "dragonKills": 0, "eligibleForProgression": true, "enemyMissingPings": 6, "enemyVisionPings": 0, "firstBloodAssist": false, "firstBloodKill": false, "firstTowerAssist": false, "firstTowerKill": false, "gameEndedInEarlySurrender": false, "gameEndedInSurrender": true, "getBackPings": 5, "goldEarned": 9605, "goldSpent": 9025, "holdPings": 0, "individualPosition": "TOP", "inhibitorKills": 0, "inhibitorTakedowns": 0, "inhibitorsLost": 0, "item0": 0, "item1": 3118, "item2": 6617, "item3": 1056, "item4": 6620, "item5": 3158, "item6": 3363, "itemsPurchased": 20, "killingSprees": 1, "kills": 5, "lane": "TOP", "largestCriticalStrike": 0, "largestKillingSpree": 5, "largestMultiKill": 1, "longestTimeSpentLiving": 991, "magicDamageDealt": 69077, "magicDamageDealtToChampions": 7670, "magicDamageTaken": 4509, "missions": {"playerScore0": 0, "playerScore1": 0, "playerScore2": 0, "playerScore3": 0, "playerScore4": 0, "playerScore5": 0, "playerScore6": 0, "playerScore7": 0, "playerScore8": 0, "playerScore9": 0, "playerScore10": 0, "playerScore11": 0}, "needVisionPings": 0, "neutralMinionsKilled": 0, "nexusKills": 0, "nexusLost": 1, "nexusTakedowns": 0, "objectivesStolen": 0, "objectivesStolenAssists": 0, "onMyWayPings": 4, "participantId": 6, "pentaKills": 0, "perks": {"statPerks": {"defense": 5001, "flex": 5010, "offense": 5005}, "styles": [{"description": "primaryStyle", "selections": [{"perk": 8005, "var1": 937, "var2": 937, "var3": 0}, {"perk": 9111, "var1": 513, "var2": 160, "var3": 0}, {"perk": 9105, "var1": 10, "var2": 20, "var3": 0}, {"perk": 8017, "var1": 490, "var2": 0, "var3": 0}], "style": 8000}, {"description": "subStyle", "selections": [{"perk": 8313, "var1": 3, "var2": 0, "var3": 0}, {"perk": 8347, "var1": 0, "var2": 0, "var3": 0}], "style": 8300}]}, "physicalDamageDealt": 19488, "physicalDamageDealtToChampions": 2883, "physicalDamageTaken": 8142, "placement": 0, "playerAugment1": 0, "playerAugment2": 0, "playerAugment3": 0, "playerAugment4": 0, "playerAugment5": 0, "playerAugment6": 0, "playerSubteamId": 0, "profileIcon": 7050, "pushPings": 1, "puuid": "EN-Qok0VumcDOiATZgaoWOwUVvT5raWfNLUJW0IxOJF2JqnsFQu6GHQ3nBPA-d5tjV-lNq7EiyQodw", "quadraKills": 0, "retreatPings": 0, "riotIdGameName": "NoRoo", "riotIdTagline": "T 1", "role": "SOLO", "roleBoundItem": 1220, "sightWardsBoughtInGame": 0, "spell1Casts": 38, "spell2Casts": 69, "spell3Casts": 79, "spell4Casts": 252, "subteamPlacement": 0, "summoner1Casts": 4, "summoner1Id": 21, "summoner2Casts": 2, "summoner2Id": 4, "summonerId": "CUCx37e2KzjIw9d3_jexe0RG0rqfTus7vjE1an0HL0tWAw", "summonerLevel": 352, "summonerName": "", "teamEarlySurrendered": false, "teamId": 200, "teamPosition": "TOP", "timeCCingOthers": 29, "timePlayed": 1342, "totalAllyJungleMinionsKilled": 0, "totalDamageDealt": 103706, "totalDamageDealtToChampions": 10646, "totalDamageShieldedOnTeammates": 6331, "totalDamageTaken": 13005, "totalEnemyJungleMinionsKilled": 0, "totalHeal": 2435, "totalHealsOnTeammates": 759, "totalMinionsKilled": 175, "totalTimeCCDealt": 467, "totalTimeSpentDead": 84, "totalUnitsHealed": 5, "tripleKills": 0, "trueDamageDealt": 15140, "trueDamageDealtToChampions": 92, "trueDamageTaken": 354, "turretKills": 0, "turretTakedowns": 1, "turretsLost": 7, "unrealKills": 0, "visionClearedPings": 0, "visionScore": 30, "visionWardsBoughtInGame": 5, "wardsKilled": 1, "wardsPlaced": 13, "win": false}, {"PlayerBehavior": {"PlayerBehavior_IsHeroInCombat": 0}, "PlayerScore0": 0, "PlayerScore1": 0, "PlayerScore10": 0, "PlayerScore11": 0, "PlayerScore2": 0, "PlayerScore3": 0, "PlayerScore4": 0, "PlayerScore5": 0, "PlayerScore6": 0, "PlayerScore7": 0, "PlayerScore8": 0, "PlayerScore9": 0, "allInPings": 2, "assistMePings": 2, "assists": 5, "baronKills": 0, "basicPings": 0, "challenges": {"12AssistStreakCount": 0, "HealFromMapSources": 101.36734771728516, "InfernalScalePickup": 0, "SWARM_DefeatAatrox": 0, "SWARM_DefeatBriar": 0, "SWARM_DefeatMiniBosses": 0, "SWARM_EvolveWeapon": 0, "SWARM_Have3Passives": 0, "SWARM_KillEnemy": 0, "SWARM_PickupGold": 0, "SWARM_ReachLevel50": 0, "SWARM_Survive15Min": 0, "SWARM_WinWith5EvolvedWeapons": 0, "abilityUses": 160, "acesBefore15Minutes": 0, "alliedJungleMonsterKills": 76, "baronTakedowns": 0, "blastConeOppositeOpponentCount": 0, "bountyGold": 0, "buffsStolen": 1, "completeSupportQuestInTime": 0, "controlWardsPlaced": 0, "damagePerMinute": 364.4131404821581, "damageTakenOnTeamPercentage": 0.28241603355968675, "dancedWithRiftHerald": 0, "deathsByEnemyChamps": 7, "dodgeSkillShotsSmallWindow": 0, "doubleAces": 0, "dragonTakedowns": 1, "earliestDragonTakedown": 942.4396753840001, "earlyLaningPhaseGoldExpAdvantage": 0, "effectiveHealAndShielding": 0, "elderDragonKillsWithOpposingSoul": 0, "elderDragonMultikills": 0, "enemyChampionImmobilizations": 4, "enemyJungleMonsterKills": 3, "epicMonsterKillsNearEnemyJungler": 0, "epicMonsterKillsWithin30SecondsOfSpawn": 0, "epicMonsterSteals": 0, "epicMonsterStolenWithoutSmite": 0, "firstTurretKilled": 0, "fistBumpParticipation": 0, "flawlessAces": 0, "fullTeamTakedown": 0, "gameLength": 1342.98021752, "goldPerMinute": 353.99185076029994, "hadOpenNexus": 0, "highestCrowdControlScore": 1, "immobilizeAndKillWithAlly": 1, "initialBuffCount": 2, "initialCrabCount": 2, "jungleCsBefore10Minutes": 76.00000011920929, "junglerKillsEarlyJungle": 0, "junglerTakedownsNearDamagedEpicMonster": 0, "kTurretsDestroyedBeforePlatesFall": 0, "kda": 0.8571428571428571, "killAfterHiddenWithAlly": 0, "killParticipation": 0.4, "killedChampTookFullTeamDamageSurvived": 0, "killingSprees": 0, "killsNearEnemyTurret": 0, "killsOnLanersEarlyJungleAsJungler": 0, "killsOnRecentlyHealedByAramPack": 0, "killsUnderOwnTurret": 0, "killsWithHelpFromEpicMonster": 0, "knockEnemyIntoTeamAndKill": 0, "landSkillShotsEarlyGame": 3, "laneMinionsFirst10Minutes": 2, "laningPhaseGoldExpAdvantage": 0, "legendaryCount": 0, "legendaryItemUsed": [6631, 3073], "lostAnInhibitor": 0, "maxCsAdvantageOnLaneOpponent": 34.000000059604645, "maxKillDeficit": 0, "maxLevelLeadLaneOpponent": 2, "mejaisFullStackInTime": 0, "moreEnemyJungleThanOpponent": -37.000000059604645, "multiKillOneSpell": 0, "multiTurretRiftHeraldCount": 0, "multikills": 0, "multikillsAfterAggressiveFlash": 0, "outerTurretExecutesBefore10Minutes": 0, "outnumberedKills": 0, "outnumberedNexusKill": 0, "perfectDragonSoulsTaken": 0, "perfectGame": 0, "pickKillWithAlly": 5, "playedChampSelectPosition": 1, "poroExplosions": 0, "quickCleanse": 0, "quickFirstTurret": 0, "quickSoloKills": 0, "riftHeraldTakedowns": 0, "saveAllyFromDeath": 0, "scuttleCrabKills": 3, "skillshotsDodged": 6, "skillshotsHit": 13, "snowballsHit": 0, "soloBaronKills": 0, "soloKills": 0, "stealthWardsPlaced": 4, "survivedSingleDigitHpCount": 0, "survivedThreeImmobilizesInFight": 0, "takedownOnFirstTurret": 0, "takedowns": 6, "takedownsAfterGainingLevelAdvantage": 0, "takedownsBeforeJungleMinionSpawn": 0, "takedownsFirstXMinutes": 5, "takedownsInAlcove": 0, "takedownsInEnemyFountain": 0, "teamBaronKills": 0, "teamDamagePercentage": 0.17818432160057784, "teamElderDragonKills": 0, "teamRiftHeraldKills": 0, "tookLargeDamageSurvived": 0, "turretPlatesTaken": 0, "turretTakedowns": 0, "turretsTakenWithRiftHerald": 0, "twentyMinionsIn3SecondsCount": 0, "twoWardsOneSweeperCount": 0, "unseenRecalls": 0, "visionScoreAdvantageLaneOpponent": -0.17348819971084595, "visionScorePerMinute": 1.0375224997400694, "voidMonsterKill": 3, "wardTakedowns": 6, "wardTakedownsBefore20M": 5, "wardsGuarded": 2}, "champExperience": 9299, "champLevel": 12, "championId": 56, "championName": "Nocturne", "championTransform": 0, "commandPings": 24, "consumablesPurchased": 1, "damageDealtToBuildings": 0, "damageDealtToEpicMonsters": 11959, "damageDealtToObjectives": 11959, "damageDealtToTurrets": 0, "damageSelfMitigated": 13555, "dangerPings": 0, "deaths": 7, "detectorWardsPlaced": 0, "doubleKills": 0, "dragonKills": 1, "eligibleForProgression": true, "enemyMissingPings": 6, "enemyVisionPings": 0, "firstBloodAssist": false, "firstBloodKill": false, "firstTowerAssist": false, "firstTowerKill": false, "gameEndedInEarlySurrender": false, "gameEndedInSurrender": true, "getBackPings": 3, "goldEarned": 7923, "goldSpent": 7450, "holdPings": 0, "individualPosition": "JUNGLE", "inhibitorKills": 0, "inhibitorTakedowns": 0, "inhibitorsLost": 0, "item0": 6631, "item1": 3073, "item2": 1001, "item3": 1036, "item4": 0, "item5": 0, "item6": 3363, "itemsPurchased": 22, "killingSprees": 0, "kills": 1, "lane": "JUNGLE", "largestCriticalStrike": 0, "largestKillingSpree": 0, "largestMultiKill": 1, "longestTimeSpentLiving": 295, "magicDamageDealt": 2615, "magicDamageDealtToChampions": 515, "magicDamageTaken": 9100, "missions": {"playerScore0": 0, "playerScore1": 0, "playerScore2": 0, "playerScore3": 0, "playerScore4": 0, "playerScore5": 0, "playerScore6": 0, "playerScore7": 0, "playerScore8": 0, "playerScore9": 0, "playerScore10": 0, "playerScore11": 0}, "needVisionPings": 0, "neutralMinionsKilled": 145, "nexusKills": 0, "nexusLost": 1, "nexusTakedowns": 0, "objectivesStolen": 0, "objectivesStolenAssists": 0, "onMyWayPings": 7, "participantId": 7, "pentaKills": 0, "perks": {"statPerks": {"defense": 5011, "flex": 5008, "offense": 5005}, "styles": [{"description": "primaryStyle", "selections": [{"perk": 8008, "var1": 272, "var2": 272, "var3": 0}, {"perk": 9111, "var1": 291, "var2": 120, "var3": 0}, {"perk": 9104, "var1": 10, "var2": 20, "var3": 0}, {"perk": 8014, "var1": 108, "var2": 0, "var3": 0}], "style": 8000}, {"description": "subStyle", "selections": [{"perk": 8137, "var1": 4, "var2": 0, "var3": 0}, {"perk": 8106, "var1": 2, "var2": 16, "var3": 0}], "style": 8100}]}, "physicalDamageDealt": 114038, "physicalDamageDealtToChampions": 7162, "physicalDamageTaken": 15918, "placement": 0, "playerAugment1": 0, "playerAugment2": 0, "playerAugment3": 0, "playerAugment4": 0, "playerAugment5": 0, "playerAugment6": 0, "playerSubteamId": 0, "profileIcon": 6504, "pushPings": 0, "puuid": "k62NydW4IOimX3WWnxx6mVaoW_P0twrcs8G4XEYzF15-qFuKiMrlNgwL6WzHDtagsDaGZKO1i43vMQ", "quadraKills": 0, "retreatPings": 0, "riotIdGameName": "YONG2", "riotIdTagline": "6666", "role": "NONE", "roleBoundItem": 1209, "sightWardsBoughtInGame": 0, "spell1Casts": 108, "spell2Casts": 12, "spell3Casts": 28, "spell4Casts": 12, "subteamPlacement": 0, "summoner1Casts": 4, "summoner1Id": 4, "summoner2Casts": 11, "summoner2Id": 11, "summonerId": "b_kXN73z6D6vIVgIMXTfKi9IshFJlboXrvelUKN7E_bSvecFNlYRFBMhmg", "summonerLevel": 480, "summonerName": "", "teamEarlySurrendered": false, "teamId": 200, "teamPosition": "JUNGLE", "timeCCingOthers": 99, "timePlayed": 1342, "totalAllyJungleMinionsKilled": 104, "totalDamageDealt": 175883, "totalDamageDealtToChampions": 8156, "totalDamageShieldedOnTeammates": 0, "totalDamageTaken": 25334, "totalEnemyJungleMinionsKilled": 12, "totalHeal": 8415, "totalHealsOnTeammates": 0, "totalMinionsKilled": 15, "totalTimeCCDealt": 407, "totalTimeSpentDead": 135, "totalUnitsHealed": 1, "tripleKills": 0, "trueDamageDealt": 59230, "trueDamageDealtToChampions": 478, "trueDamageTaken": 314, "turretKills": 0, "turretTakedowns": 0, "turretsLost": 7, "unrealKills": 0, "visionClearedPings": 0, "visionScore": 23, "visionWardsBoughtInGame": 0, "wardsKilled": 6, "wardsPlaced": 7, "win": false}, {"PlayerBehavior": {"PlayerBehavior_IsHeroInCombat": 0}, "PlayerScore0": 0, "PlayerScore1": 0, "PlayerScore10": 0, "PlayerScore11": 0, "PlayerScore2": 0, "PlayerScore3": 0, "PlayerScore4": 0, "PlayerScore5": 0, "PlayerScore6": 0, "PlayerScore7": 0, "PlayerScore8": 0, "PlayerScore9": 0, "allInPings": 0, "assistMePings": 0, "assists": 4, "baronKills": 0, "basicPings": 0, "challenges": {"12AssistStreakCount": 0, "HealFromMapSources": 172, "InfernalScalePickup": 0, "SWARM_DefeatAatrox": 0, "SWARM_DefeatBriar": 0, "SWARM_DefeatMiniBosses": 0, "SWARM_EvolveWeapon": 0, "SWARM_Have3Passives": 0, "SWARM_KillEnemy": 0, "SWARM_PickupGold": 0, "SWARM_ReachLevel50": 0, "SWARM_Survive15Min": 0, "SWARM_WinWith5EvolvedWeapons": 0, "abilityUses": 179, "acesBefore15Minutes": 0, "alliedJungleMonsterKills": 1, "baronTakedowns": 0, "blastConeOppositeOpponentCount": 0, "bountyGold": 0, "buffsStolen": 0, "completeSupportQuestInTime": 0, "controlWardTimeCoverageInRiverOrEnemyHalf": 0.8749887602074824, "controlWardsPlaced": 4, "damagePerMinute": 636.9474843593599, "damageTakenOnTeamPercentage": 0.21353556904185522, "dancedWithRiftHerald": 0, "deathsByEnemyChamps": 3, "dodgeSkillShotsSmallWindow": 0, "doubleAces": 0, "dragonTakedowns": 1, "earliestDragonTakedown": 942.4396753840001, "earlyLaningPhaseGoldExpAdvantage": 0, "effectiveHealAndShielding": 0, "elderDragonKillsWithOpposingSoul": 0, "elderDragonMultikills": 0, "enemyChampionImmobilizations": 13, "enemyJungleMonsterKills": 0, "epicMonsterKillsNearEnemyJungler": 0, "epicMonsterKillsWithin30SecondsOfSpawn": 0, "epicMonsterSteals": 0, "epicMonsterStolenWithoutSmite": 0, "firstTurretKilled": 0, "fistBumpParticipation": 0, "flawlessAces": 0, "fullTeamTakedown": 0, "gameLength": 1342.98021752, "getTakedownsInAllLanesEarlyJungleAsLaner": 0, "goldPerMinute": 410.6553067054295, "hadOpenNexus": 0, "immobilizeAndKillWithAlly": 2, "initialBuffCount": 0, "initialCrabCount": 0, "jungleCsBefore10Minutes": 4, "junglerTakedownsNearDamagedEpicMonster": 0, "kTurretsDestroyedBeforePlatesFall": 0, "kda": 3.3333333333333335, "killAfterHiddenWithAlly": 0, "killParticipation": 0.6666666666666666, "killedChampTookFullTeamDamageSurvived": 0, "killingSprees": 1, "killsNearEnemyTurret": 1, "killsOnOtherLanesEarlyJungleAsLaner": 0, "killsOnRecentlyHealedByAramPack": 0, "killsUnderOwnTurret": 1, "killsWithHelpFromEpicMonster": 0, "knockEnemyIntoTeamAndKill": 0, "landSkillShotsEarlyGame": 0, "laneMinionsFirst10Minutes": 71, "laningPhaseGoldExpAdvantage": 0, "legendaryCount": 0, "legendaryItemUsed": [3116, 2503], "lostAnInhibitor": 0, "maxCsAdvantageOnLaneOpponent": 1, "maxKillDeficit": 0, "maxLevelLeadLaneOpponent": 1, "mejaisFullStackInTime": 0, "moreEnemyJungleThanOpponent": 0, "multiKillOneSpell": 0, "multiTurretRiftHeraldCount": 0, "multikills": 1, "multikillsAfterAggressiveFlash": 0, "outerTurretExecutesBefore10Minutes": 0, "outnumberedKills": 0, "outnumberedNexusKill": 0, "perfectDragonSoulsTaken": 0, "perfectGame": 0, "pickKillWithAlly": 8, "playedChampSelectPosition": 1, "poroExplosions": 0, "quickCleanse": 0, "quickFirstTurret": 0, "quickSoloKills": 0, "riftHeraldTakedowns": 0, "saveAllyFromDeath": 0, "scuttleCrabKills": 0, "skillshotsDodged": 6, "skillshotsHit": 0, "snowballsHit": 0, "soloBaronKills": 0, "soloKills": 0, "stealthWardsPlaced": 5, "survivedSingleDigitHpCount": 0, "survivedThreeImmobilizesInFight": 0, "takedownOnFirstTurret": 0, "takedowns": 10, "takedownsAfterGainingLevelAdvantage": 1, "takedownsBeforeJungleMinionSpawn": 0, "takedownsFirstXMinutes": 8, "takedownsInAlcove": 0, "takedownsInEnemyFountain": 0, "teamBaronKills": 0, "teamDamagePercentage": 0.31144336684896234, "teamElderDragonKills": 0, "teamRiftHeraldKills": 0, "tookLargeDamageSurvived": 0, "turretPlatesTaken": 3, "turretTakedowns": 0, "turretsTakenWithRiftHerald": 0, "twentyMinionsIn3SecondsCount": 0, "twoWardsOneSweeperCount": 0, "unseenRecalls": 0, "visionScoreAdvantageLaneOpponent": -0.1302013397216797, "visionScorePerMinute": 1.2393382393635022, "voidMonsterKill": 3, "wardTakedowns": 1, "wardTakedownsBefore20M": 1, "wardsGuarded": 1}, "champExperience": 11062, "champLevel": 13, "championId": 136, "championName": "AurelionSol", "championTransform": 0, "commandPings": 7, "consumablesPurchased": 6, "damageDealtToBuildings": 2905, "damageDealtToEpicMonsters": 4652, "damageDealtToObjectives": 7558, "damageDealtToTurrets": 2905, "damageSelfMitigated": 7937, "dangerPings": 0, "deaths": 3, "detectorWardsPlaced": 4, "doubleKills": 1, "dragonKills": 0, "eligibleForProgression": true, "enemyMissingPings": 1, "enemyVisionPings": 2, "firstBloodAssist": false, "firstBloodKill": false, "firstTowerAssist": false, "firstTowerKill": false, "gameEndedInEarlySurrender": false, "gameEndedInSurrender": true, "getBackPings": 4, "goldEarned": 9191, "goldSpent": 8700, "holdPings": 0, "individualPosition": "MIDDLE", "inhibitorKills": 0, "inhibitorTakedowns": 0, "inhibitorsLost": 0, "item0": 2503, "item1": 3116, "item2": 1058, "item3": 1082, "item4": 3175, "item5": 1056, "item6": 3363, "itemsPurchased": 28, "killingSprees": 1, "kills": 6, "lane": "MIDDLE", "largestCriticalStrike": 0, "largestKillingSpree": 5, "largestMultiKill": 2, "longestTimeSpentLiving": 641, "magicDamageDealt": 72401, "magicDamageDealtToChampions": 14147, "magicDamageTaken": 10510, "missions": {"playerScore0": 0, "playerScore1": 0, "playerScore2": 0, "playerScore3": 0, "playerScore4": 0, "playerScore5": 0, "playerScore6": 0, "playerScore7": 0, "playerScore8": 0, "playerScore9": 0, "playerScore10": 0, "playerScore11": 0}, "needVisionPings": 0, "neutralMinionsKilled": 4, "nexusKills": 0, "nexusLost": 1, "nexusTakedowns": 0, "objectivesStolen": 0, "objectivesStolenAssists": 0, "onMyWayPings": 48, "participantId": 8, "pentaKills": 0, "perks": {"statPerks": {"defense": 5011, "flex": 5008, "offense": 5008}, "styles": [{"description": "primaryStyle", "selections": [{"perk": 8229, "var1": 1657, "var2": 0, "var3": 0}, {"perk": 8226, "var1": 250, "var2": 789, "var3": 0}, {"perk": 8210, "var1": 4, "var2": 0, "var3": 0}, {"perk": 8237, "var1": 636, "var2": 0, "var3": 0}], "style": 8200}, {"description": "subStyle", "selections": [{"perk": 8304, "var1": 9, "var2": 0, "var3": 0}, {"perk": 8313, "var1": 3, "var2": 0, "var3": 0}], "style": 8300}]}, "physicalDamageDealt": 5152, "physicalDamageDealtToChampions": 0, "physicalDamageTaken": 8294, "placement": 0, "playerAugment1": 0, "playerAugment2": 0, "playerAugment3": 0, "playerAugment4": 0, "playerAugment5": 0, "playerAugment6": 0, "playerSubteamId": 0, "profileIcon": 4074, "pushPings": 1, "puuid": "1bVScljhCg5Rku3G5jTwBjzTLQZRGsLc-l5OOUoYZNxNaCybvTPdrJgCmWLRfaZyAAzWuq20r0rB9w", "quadraKills": 0, "retreatPings": 0, "riotIdGameName": "M G", "riotIdTagline": "2821", "role": "SOLO", "roleBoundItem": 1206, "sightWardsBoughtInGame": 0, "spell1Casts": 98, "spell2Casts": 30, "spell3Casts": 45, "spell4Casts": 6, "subteamPlacement": 0, "summoner1Casts": 3, "summoner1Id": 12, "summoner2Casts": 1, "summoner2Id": 4, "summonerId": "TkQoESWuo27Rym4m47aS9ldZU7hDF-8gE8Hj5OyExllc-o2F", "summonerLevel": 987, "summonerName": "", "teamEarlySurrendered": false, "teamId": 200, "teamPosition": "MIDDLE", "timeCCingOthers": 14, "timePlayed": 1342, "totalAllyJungleMinionsKilled": 4, "totalDamageDealt": 83062, "totalDamageDealtToChampions": 14256, "totalDamageShieldedOnTeammates": 0, "totalDamageTaken": 19155, "totalEnemyJungleMinionsKilled": 0, "totalHeal": 3845, "totalHealsOnTeammates": 0, "totalMinionsKilled": 175, "totalTimeCCDealt": 312, "totalTimeSpentDead": 54, "totalUnitsHealed": 1, "tripleKills": 0, "trueDamageDealt": 5508, "trueDamageDealtToChampions": 109, "trueDamageTaken": 350, "turretKills": 0, "turretTakedowns": 0, "turretsLost": 7, "unrealKills": 0, "visionClearedPings": 0, "visionScore": 27, "visionWardsBoughtInGame": 4, "wardsKilled": 1, "wardsPlaced": 12, "win": false}, {"PlayerBehavior": {"PlayerBehavior_IsHeroInCombat": 0}, "PlayerScore0": 0, "PlayerScore1": 0, "PlayerScore10": 0, "PlayerScore11": 0, "PlayerScore2": 0, "PlayerScore3": 0, "PlayerScore4": 0, "PlayerScore5": 0, "PlayerScore6": 0, "PlayerScore7": 0, "PlayerScore8": 0, "PlayerScore9": 0, "allInPings": 0, "assistMePings": 0, "assists": 3, "baronKills": 0, "basicPings": 0, "challenges": {"12AssistStreakCount": 0, "HealFromMapSources": 414, "InfernalScalePickup": 0, "SWARM_DefeatAatrox": 0, "SWARM_DefeatBriar": 0, "SWARM_DefeatMiniBosses": 0, "SWARM_EvolveWeapon": 0, "SWARM_Have3Passives": 0, "SWARM_KillEnemy": 0, "SWARM_PickupGold": 0, "SWARM_ReachLevel50": 0, "SWARM_Survive15Min": 0, "SWARM_WinWith5EvolvedWeapons": 0, "abilityUses": 101, "acesBefore15Minutes": 0, "alliedJungleMonsterKills": 1, "baronTakedowns": 0, "blastConeOppositeOpponentCount": 0, "bountyGold": 177.19638061523438, "buffsStolen": 0, "completeSupportQuestInTime": 0, "controlWardsPlaced": 1, "damagePerMinute": 397.2625327582718, "damageTakenOnTeamPercentage": 0.18303833217048562, "dancedWithRiftHerald": 0, "deathsByEnemyChamps": 8, "dodgeSkillShotsSmallWindow": 0, "doubleAces": 0, "dragonTakedowns": 0, "earlyLaningPhaseGoldExpAdvantage": 0, "effectiveHealAndShielding": 0, "elderDragonKillsWithOpposingSoul": 0, "elderDragonMultikills": 0, "enemyChampionImmobilizations": 4, "enemyJungleMonsterKills": 0, "epicMonsterKillsNearEnemyJungler": 0, "epicMonsterKillsWithin30SecondsOfSpawn": 0, "epicMonsterSteals": 0, "epicMonsterStolenWithoutSmite": 0, "firstTurretKilled": 0, "fistBumpParticipation": 0, "flawlessAces": 0, "fullTeamTakedown": 0, "gameLength": 1342.98021752, "getTakedownsInAllLanesEarlyJungleAsLaner": 0, "goldPerMinute": 414.51797005748494, "hadOpenNexus": 0, "immobilizeAndKillWithAlly": 1, "initialBuffCount": 0, "initialCrabCount": 0, "jungleCsBefore10Minutes": 0, "junglerTakedownsNearDamagedEpicMonster": 0, "kTurretsDestroyedBeforePlatesFall": 1, "kda": 0.75, "killAfterHiddenWithAlly": 0, "killParticipation": 0.4, "killedChampTookFullTeamDamageSurvived": 0, "killingSprees": 0, "killsNearEnemyTurret": 1, "killsOnOtherLanesEarlyJungleAsLaner": 0, "killsOnRecentlyHealedByAramPack": 0, "killsUnderOwnTurret": 0, "killsWithHelpFromEpicMonster": 0, "knockEnemyIntoTeamAndKill": 0, "landSkillShotsEarlyGame": 6, "laneMinionsFirst10Minutes": 48, "laningPhaseGoldExpAdvantage": 0, "legendaryCount": 0, "legendaryItemUsed": [2523, 3094], "lostAnInhibitor": 0, "maxCsAdvantageOnLaneOpponent": 0, "maxKillDeficit": 0, "maxLevelLeadLaneOpponent": 0, "mejaisFullStackInTime": 0, "moreEnemyJungleThanOpponent": 0, "multiKillOneSpell": 0, "multiTurretRiftHeraldCount": 0, "multikills": 0, "multikillsAfterAggressiveFlash": 0, "outerTurretExecutesBefore10Minutes": 0, "outnumberedKills": 0, "outnumberedNexusKill": 0, "perfectDragonSoulsTaken": 0, "perfectGame": 0, "pickKillWithAlly": 5, "playedChampSelectPosition": 1, "poroExplosions": 0, "quickCleanse": 0, "quickFirstTurret": 0, "quickSoloKills": 0, "riftHeraldTakedowns": 0, "saveAllyFromDeath": 0, "scuttleCrabKills": 0, "skillshotsDodged": 4, "skillshotsHit": 17, "snowballsHit": 0, "soloBaronKills": 0, "soloKills": 0, "stealthWardsPlaced": 6, "survivedSingleDigitHpCount": 0, "survivedThreeImmobilizesInFight": 0, "takedownOnFirstTurret": 0, "takedowns": 6, "takedownsAfterGainingLevelAdvantage": 0, "takedownsBeforeJungleMinionSpawn": 0, "takedownsFirstXMinutes": 5, "takedownsInAlcove": 0, "takedownsInEnemyFountain": 0, "teamBaronKills": 0, "teamDamagePercentage": 0.19424643909163786, "teamElderDragonKills": 0, "teamRiftHeraldKills": 0, "tookLargeDamageSurvived": 0, "turretPlatesTaken": 3, "turretTakedowns": 1, "turretsTakenWithRiftHerald": 0, "twentyMinionsIn3SecondsCount": 0, "twoWardsOneSweeperCount": 0, "unseenRecalls": 0, "visionScoreAdvantageLaneOpponent": -0.2332749366760254, "visionScorePerMinute": 0.7017347348512019, "voidMonsterKill": 0, "wardTakedowns": 3, "wardTakedownsBefore20M": 3, "wardsGuarded": 0}, "champExperience": 8420, "champLevel": 11, "championId": 51, "championName": "Caitlyn", "championTransform": 0, "commandPings": 7, "consumablesPurchased": 2, "damageDealtToBuildings": 4344, "damageDealtToEpicMonsters": 675, "damageDealtToObjectives": 5020, "damageDealtToTurrets": 4344, "damageSelfMitigated": 7873, "dangerPings": 0, "deaths": 8, "detectorWardsPlaced": 1, "doubleKills": 0, "dragonKills": 0, "eligibleForProgression": true, "enemyMissingPings": 6, "enemyVisionPings": 0, "firstBloodAssist": false, "firstBloodKill": false, "firstTowerAssist": false, "firstTowerKill": false, "gameEndedInEarlySurrender": false, "gameEndedInSurrender": true, "getBackPings": 1, "goldEarned": 9278, "goldSpent": 9100, "holdPings": 0, "individualPosition": "BOTTOM", "inhibitorKills": 0, "inhibitorTakedowns": 0, "inhibitorsLost": 0, "item0": 3094, "item1": 0, "item2": 2523, "item3": 1055, "item4": 1038, "item5": 1037, "item6": 3363, "itemsPurchased": 16, "killingSprees": 0, "kills": 3, "lane": "BOTTOM", "largestCriticalStrike": 711, "largestKillingSpree": 0, "largestMultiKill": 1, "longestTimeSpentLiving": 528, "magicDamageDealt": 1521, "magicDamageDealtToChampions": 491, "magicDamageTaken": 5881, "missions": {"playerScore0": 0, "playerScore1": 0, "playerScore2": 0, "playerScore3": 0, "playerScore4": 0, "playerScore5": 0, "playerScore6": 0, "playerScore7": 0, "playerScore8": 0, "playerScore9": 0, "playerScore10": 0, "playerScore11": 0}, "needVisionPings": 0, "neutralMinionsKilled": 0, "nexusKills": 0, "nexusLost": 1, "nexusTakedowns": 0, "objectivesStolen": 0, "objectivesStolenAssists": 0, "onMyWayPings": 2, "participantId": 9, "pentaKills": 0, "perks": {"statPerks": {"defense": 5011, "flex": 5008, "offense": 5005}, "styles": [{"description": "primaryStyle", "selections": [{"perk": 8008, "var1": 52, "var2": 52, "var3": 0}, {"perk": 8009, "var1": 741, "var2": 0, "var3": 0}, {"perk": 9103, "var1": 0, "var2": 0, "var3": 0}, {"perk": 8017, "var1": 469, "var2": 0, "var3": 0}], "style": 8000}, {"description": "subStyle", "selections": [{"perk": 8313, "var1": 3, "var2": 0, "var3": 0}, {"perk": 8321, "var1": 408, "var2": 0, "var3": 0}], "style": 8300}]}, "physicalDamageDealt": 87659, "physicalDamageDealtToChampions": 8400, "physicalDamageTaken": 10043, "placement": 0, "playerAugment1": 0, "playerAugment2": 0, "playerAugment3": 0, "playerAugment4": 0, "playerAugment5": 0, "playerAugment6": 0, "playerSubteamId": 0, "profileIcon": 5493, "pushPings": 0, "puuid": "DgqLeWUzndH39nqp7y-ziA39kQHcrcxYPXqGyjG9TeNI3XHeaqt75EOoEDOFFuVZ5gW7dV5ra4_GAw", "quadraKills": 0, "retreatPings": 0, "riotIdGameName": "Robin", "riotIdTagline": "星期日", "role": "CARRY", "roleBoundItem": 1001, "sightWardsBoughtInGame": 0, "spell1Casts": 50, "spell2Casts": 31, "spell3Casts": 17, "spell4Casts": 3, "subteamPlacement": 0, "summoner1Casts": 3, "summoner1Id": 4, "summoner2Casts": 3, "summoner2Id": 21, "summonerId": "ejVGgrftYuHTA3cbHWXMqd3xsW3y04WlIbIo1ErDWmHXHNQ", "summonerLevel": 408, "summonerName": "", "teamEarlySurrendered": false, "teamId": 200, "teamPosition": "BOTTOM", "timeCCingOthers": 8, "timePlayed": 1342, "totalAllyJungleMinionsKilled": 0, "totalDamageDealt": 91078, "totalDamageDealtToChampions": 8891, "totalDamageShieldedOnTeammates": 0, "totalDamageTaken": 16419, "totalEnemyJungleMinionsKilled": 0, "totalHeal": 1814, "totalHealsOnTeammates": 0, "totalMinionsKilled": 165, "totalTimeCCDealt": 44, "totalTimeSpentDead": 171, "totalUnitsHealed": 1, "tripleKills": 0, "trueDamageDealt": 1896, "trueDamageDealtToChampions": 0, "trueDamageTaken": 494, "turretKills": 1, "turretTakedowns": 1, "turretsLost": 7, "unrealKills": 0, "visionClearedPings": 0, "visionScore": 15, "visionWardsBoughtInGame": 1, "wardsKilled": 3, "wardsPlaced": 8, "win": false}, {"PlayerBehavior": {"PlayerBehavior_IsHeroInCombat": 0}, "PlayerScore0": 0, "PlayerScore1": 0, "PlayerScore10": 0, "PlayerScore11": 0, "PlayerScore2": 0, "PlayerScore3": 0, "PlayerScore4": 0, "PlayerScore5": 0, "PlayerScore6": 0, "PlayerScore7": 0, "PlayerScore8": 0, "PlayerScore9": 0, "allInPings": 1, "assistMePings": 5, "assists": 5, "baronKills": 0, "basicPings": 0, "challenges": {"12AssistStreakCount": 0, "HealFromMapSources": 140.77140045166016, "InfernalScalePickup": 0, "SWARM_DefeatAatrox": 0, "SWARM_DefeatBriar": 0, "SWARM_DefeatMiniBosses": 0, "SWARM_EvolveWeapon": 0, "SWARM_Have3Passives": 0, "SWARM_KillEnemy": 0, "SWARM_PickupGold": 0, "SWARM_ReachLevel50": 0, "SWARM_Survive15Min": 0, "SWARM_WinWith5EvolvedWeapons": 0, "abilityUses": 102, "acesBefore15Minutes": 0, "alliedJungleMonsterKills": 0, "baronTakedowns": 0, "blastConeOppositeOpponentCount": 0, "bountyGold": 0, "buffsStolen": 0, "completeSupportQuestInTime": 0, "controlWardTimeCoverageInRiverOrEnemyHalf": 0.29969001279648866, "controlWardsPlaced": 3, "damagePerMinute": 170.88136153615372, "damageTakenOnTeamPercentage": 0.17602407981986948, "dancedWithRiftHerald": 0, "deathsByEnemyChamps": 5, "dodgeSkillShotsSmallWindow": 0, "doubleAces": 0, "dragonTakedowns": 0, "earlyLaningPhaseGoldExpAdvantage": 0, "effectiveHealAndShielding": 7138.16064453125, "elderDragonKillsWithOpposingSoul": 0, "elderDragonMultikills": 0, "enemyChampionImmobilizations": 2, "enemyJungleMonsterKills": 0, "epicMonsterKillsNearEnemyJungler": 0, "epicMonsterKillsWithin30SecondsOfSpawn": 0, "epicMonsterSteals": 0, "epicMonsterStolenWithoutSmite": 0, "firstTurretKilled": 0, "fistBumpParticipation": 0, "flawlessAces": 0, "fullTeamTakedown": 0, "gameLength": 1342.98021752, "getTakedownsInAllLanesEarlyJungleAsLaner": 0, "goldPerMinute": 237.14638252732271, "hadOpenNexus": 0, "immobilizeAndKillWithAlly": 0, "initialBuffCount": 0, "initialCrabCount": 0, "jungleCsBefore10Minutes": 0, "junglerTakedownsNearDamagedEpicMonster": 0, "kTurretsDestroyedBeforePlatesFall": 0, "kda": 1, "killAfterHiddenWithAlly": 0, "killParticipation": 0.3333333333333333, "killedChampTookFullTeamDamageSurvived": 0, "killingSprees": 0, "killsNearEnemyTurret": 0, "killsOnOtherLanesEarlyJungleAsLaner": 0, "killsOnRecentlyHealedByAramPack": 0, "killsUnderOwnTurret": 0, "killsWithHelpFromEpicMonster": 0, "knockEnemyIntoTeamAndKill": 0, "landSkillShotsEarlyGame": 18, "laneMinionsFirst10Minutes": 16, "laningPhaseGoldExpAdvantage": 0, "legendaryCount": 0, "legendaryItemUsed": [6620, 3870], "lostAnInhibitor": 0, "maxCsAdvantageOnLaneOpponent": 8, "maxKillDeficit": 0, "maxLevelLeadLaneOpponent": 1, "mejaisFullStackInTime": 0, "moreEnemyJungleThanOpponent": 0, "multiKillOneSpell": 0, "multiTurretRiftHeraldCount": 0, "multikills": 0, "multikillsAfterAggressiveFlash": 0, "outerTurretExecutesBefore10Minutes": 0, "outnumberedKills": 0, "outnumberedNexusKill": 0, "perfectDragonSoulsTaken": 0, "perfectGame": 0, "pickKillWithAlly": 4, "playedChampSelectPosition": 1, "poroExplosions": 0, "quickCleanse": 0, "quickFirstTurret": 0, "quickSoloKills": 0, "riftHeraldTakedowns": 0, "saveAllyFromDeath": 2, "scuttleCrabKills": 0, "skillshotsDodged": 4, "skillshotsHit": 32, "snowballsHit": 0, "soloBaronKills": 0, "soloKills": 0, "stealthWardsPlaced": 26, "survivedSingleDigitHpCount": 0, "survivedThreeImmobilizesInFight": 0, "takedownOnFirstTurret": 0, "takedowns": 5, "takedownsAfterGainingLevelAdvantage": 0, "takedownsBeforeJungleMinionSpawn": 0, "takedownsFirstXMinutes": 4, "takedownsInAlcove": 0, "takedownsInEnemyFountain": 0, "teamBaronKills": 0, "teamDamagePercentage": 0.08355455963859075, "teamElderDragonKills": 0, "teamRiftHeraldKills": 0, "tookLargeDamageSurvived": 0, "turretPlatesTaken": 0, "turretTakedowns": 0, "turretsTakenWithRiftHerald": 0, "twentyMinionsIn3SecondsCount": 0, "twoWardsOneSweeperCount": 0, "unseenRecalls": 0, "visionScoreAdvantageLaneOpponent": -0.19008320569992065, "visionScorePerMinute": 2.717594459346665, "voidMonsterKill": 0, "wardTakedowns": 7, "wardTakedownsBefore20M": 5, "wardsGuarded": 2}, "champExperience": 5167, "champLevel": 9, "championId": 16, "championName": "Soraka", "championTransform": 0, "commandPings": 24, "consumablesPurchased": 8, "damageDealtToBuildings": 0, "damageDealtToEpicMonsters": 0, "damageDealtToObjectives": 0, "damageDealtToTurrets": 0, "damageSelfMitigated": 6101, "dangerPings": 0, "deaths": 5, "detectorWardsPlaced": 3, "doubleKills": 0, "dragonKills": 0, "eligibleForProgression": true, "enemyMissingPings": 10, "enemyVisionPings": 3, "firstBloodAssist": false, "firstBloodKill": false, "firstTowerAssist": false, "firstTowerKill": false, "gameEndedInEarlySurrender": false, "gameEndedInSurrender": true, "getBackPings": 0, "goldEarned": 5308, "goldSpent": 4970, "holdPings": 0, "individualPosition": "UTILITY", "inhibitorKills": 0, "inhibitorTakedowns": 0, "inhibitorsLost": 0, "item0": 3870, "item1": 6620, "item2": 3158, "item3": 3067, "item4": 2022, "item5": 0, "item6": 3364, "itemsPurchased": 23, "killingSprees": 0, "kills": 0, "lane": "BOTTOM", "largestCriticalStrike": 0, "largestKillingSpree": 0, "largestMultiKill": 0, "longestTimeSpentLiving": 385, "magicDamageDealt": 6190, "magicDamageDealtToChampions": 2918, "magicDamageTaken": 9297, "missions": {"playerScore0": 0, "playerScore1": 0, "playerScore2": 0, "playerScore3": 0, "playerScore4": 0, "playerScore5": 0, "playerScore6": 0, "playerScore7": 0, "playerScore8": 0, "playerScore9": 0, "playerScore10": 0, "playerScore11": 0}, "needVisionPings": 0, "neutralMinionsKilled": 0, "nexusKills": 0, "nexusLost": 1, "nexusTakedowns": 0, "objectivesStolen": 0, "objectivesStolenAssists": 0, "onMyWayPings": 6, "participantId": 10, "pentaKills": 0, "perks": {"statPerks": {"defense": 5011, "flex": 5008, "offense": 5007}, "styles": [{"description": "primaryStyle", "selections": [{"perk": 8214, "var1": 375, "var2": 341, "var3": 0}, {"perk": 8224, "var1": 22, "var2": 348, "var3": 0}, {"perk": 8234, "var1": 9099, "var2": 0, "var3": 0}, {"perk": 8237, "var1": 290, "var2": 0, "var3": 0}], "style": 8200}, {"description": "subStyle", "selections": [{"perk": 8463, "var1": 343, "var2": 0, "var3": 0}, {"perk": 8453, "var1": 1273, "var2": 149, "var3": 0}], "style": 8400}]}, "physicalDamageDealt": 3197, "physicalDamageDealtToChampions": 905, "physicalDamageTaken": 6447, "placement": 0, "playerAugment1": 0, "playerAugment2": 0, "playerAugment3": 0, "playerAugment4": 0, "playerAugment5": 0, "playerAugment6": 0, "playerSubteamId": 0, "profileIcon": 7015, "pushPings": 0, "puuid": "VQYKg7nVyGyAECILMq0k4VzClnDlA04xcUOhcz_lr4dsUVMQO29EJo_HQwDm1c7FvHt7ciSRiyOG7A", "quadraKills": 0, "retreatPings": 2, "riotIdGameName": "panzhexiatian", "riotIdTagline": "KR1", "role": "SUPPORT", "roleBoundItem": 1208, "sightWardsBoughtInGame": 0, "spell1Casts": 52, "spell2Casts": 28, "spell3Casts": 18, "spell4Casts": 4, "subteamPlacement": 0, "summoner1Casts": 5, "summoner1Id": 7, "summoner2Casts": 3, "summoner2Id": 4, "summonerId": "Cw5LA-tAcXw6IHqD3FbIP54c18-a_f08g2g1sYyfzVC3Har-uDt2sUVR7w", "summonerLevel": 246, "summonerName": "", "teamEarlySurrendered": false, "teamId": 200, "teamPosition": "UTILITY", "timeCCingOthers": 21, "timePlayed": 1342, "totalAllyJungleMinionsKilled": 0, "totalDamageDealt": 10515, "totalDamageDealtToChampions": 3824, "totalDamageShieldedOnTeammates": 375, "totalDamageTaken": 15790, "totalEnemyJungleMinionsKilled": 0, "totalHeal": 12419, "totalHealsOnTeammates": 6762, "totalMinionsKilled": 31, "totalTimeCCDealt": 88, "totalTimeSpentDead": 81, "totalUnitsHealed": 5, "tripleKills": 0, "trueDamageDealt": 1127, "trueDamageDealtToChampions": 0, "trueDamageTaken": 44, "turretKills": 0, "turretTakedowns": 0, "turretsLost": 7, "unrealKills": 0, "visionClearedPings": 0, "visionScore": 60, "visionWardsBoughtInGame": 5, "wardsKilled": 6, "wardsPlaced": 29, "win": false}], "platformId": "KR", "queueId": 420, "teams": [{"bans": [{"championId": 35, "pickTurn": 1}, {"championId": 24, "pickTurn": 2}, {"championId": 142, "pickTurn": 3}, {"championId": 166, "pickTurn": 4}, {"championId": 34, "pickTurn": 5}], "feats": {"EPIC_MONSTER_KILL": {"featState": 0}, "FIRST_BLOOD": {"featState": 0}, "FIRST_TURRET": {"featState": 0}}, "objectives": {"atakhan": {"first": false, "kills": 0}, "baron": {"first": true, "kills": 1}, "champion": {"first": true, "kills": 26}, "dragon": {"first": true, "kills": 2}, "horde": {"first": false, "kills": 0}, "inhibitor": {"first": false, "kills": 0}, "riftHerald": {"first": true, "kills": 1}, "tower": {"first": true, "kills": 7}}, "teamId": 100, "win": true}, {"bans": [{"championId": -1, "pickTurn": 6}, {"championId": 7, "pickTurn": 7}, {"championId": 107, "pickTurn": 8}, {"championId": 104, "pickTurn": 9}, {"championId": 9, "pickTurn": 10}], "feats": {"EPIC_MONSTER_KILL": {"featState": 0}, "FIRST_BLOOD": {"featState": 0}, "FIRST_TURRET": {"featState": 0}}, "objectives": {"atakhan": {"first": false, "kills": 0}, "baron": {"first": false, "kills": 0}, "champion": {"first": false, "kills": 15}, "dragon": {"first": false, "kills": 1}, "horde": {"first": true, "kills": 3}, "inhibitor": {"first": false, "kills": 0}, "riftHerald": {"first": false, "kills": 0}, "tower": {"first": false, "kills": 1}}, "teamId": 200, "win": false}], "tournamentCode": ""}}